Workbook
Name Leeftijd: Vakantie!$D$2:$D$9
Name Account: CRM!$A$2:$A$546
Name CRM: CRM!$A$2:$O$546
Name Schalen25: Schalen25!$A$4:$I$61
Name Mins: Vakantie!$B$2:$B$9
Name Vakantie: Vakantie!$A$2:$E$9

Sheet Form
C1: =FillIn!H4 -> DeNeX Uitzendbureau B.V.
C2: New Employee Application Form
C4: Salutation | E4: =IF(D4="dhr.","de heer","mevrouw") -> mevrouw | G4: Bank account | I4: =UPPER(H4)
C6: Initials | E6: =UPPER(SUBSTITUTE(SUBSTITUTE(SUBSTITUTE(MID(SUBSTITUTE(D6,".",""),1,1)&"."&MID(SUBSTITUTE(D6,".",""),2,1)&"."&MID(SUBSTITUTE(D6,".",""),3,1)&"."&MID(SUBSTITUTE(D6,".",""),4,1)&".","....","."),"...","."),"..",".")) -> . | G6: Date of birth
C8: Last Name | E8: =D4&" "&E6&" "&PROPER(D8) -> . | G8: Employment date | I8: =PROPER(D8)
C10: Address/Street | E10: =IF(J10="month",H10,IF(J10="year",H10*12,ROUND(H10/4,2))) | F10: =E10&" maanden" -> maanden | G10: Contract duration | I10: =PROPER(D10) | J10: month | O10: =E10
O11: =E11
C12: Postal Code/City | E12: =IF(J12="month",H12,IF(J12="year",H12*12,ROUND(H12/4,2))) -> 1 | G12: Probationary period | H12: 1 | I12: =IF(E12>1,E12&" maanden"," maand") -> maand | J12: month | O12: =E12 -> 1
C14: Country | E14: =EDATE(H8,H10)-1 -> -1 | F14: =UPPER(IF(LEFT(D14,1)="b","Bulgarije",IF(LEFT(D14,1)="n","Nederland",D14))) | G14: Hourly wage | H14: D5
C16: Telephone | E16: =H16&" uur "&J16 -> 40 uur per week | G16: Working hours | H16: 40 | I16: uur | J16: per week
C18: Email | G18: Position | H18: Driver | I18: =PROPER(H18) -> Driver | M18: =E18
C20: KIWA | M20: =E20
C22: BSN | M22: =E22
C26: New ZZP Application Form
C28: Salutation | E28: =IF(D28="dhr.","de heer","mevrouw") -> mevrouw
C30: Initials | E30: =UPPER(SUBSTITUTE(SUBSTITUTE(SUBSTITUTE(MID(SUBSTITUTE(D30,".",""),1,1)&"."&MID(SUBSTITUTE(D30,".",""),2,1)&"."&MID(SUBSTITUTE(D30,".",""),3,1)&"."&MID(SUBSTITUTE(D30,".",""),4,1)&".","....","."),"...","."),"..",".")) -> .
C32: Last Name | E32: =D28&" "&E30&" "&PROPER(D32) -> .
C34: Address/Street | E34: =IF(F57="month",D57,IF(F57="year",D57*12,ROUND(D57/4,2))) | F34: =E34&" maanden" -> maanden
C36: Postal Code/City | E36: =IF(F59="month",D59,IF(F59="year",D59*12,ROUND(D59/4,2))) -> 1
C38: Country | E38: =EDATE(D55,D57)-1 -> -1 | F38: =UPPER(IF(LEFT(D38,1)="b","Bulgarije",IF(LEFT(D38,1)="n","Nederland",D38)))
C40: Telephone | E40: =D63&" uur "&F63 -> 40 uur per week
C42: Email
C44: KvK Number
C46: BSN
C49: Merge Driver, Truck, Client
C51: Bank account | E51: =UPPER(D51)
C53: Date of birth
C55: Employment date | E55: =PROPER(D32)
C57: Contract duration | E57: =PROPER(D34) | F57: month
C59: Probationary period | D59: 1 | E59: =IF(E36>1,E36&" maanden"," maand") -> maand | F59: month
C61: Hourly wage
C63: Working hours | D63: 40 | E63: uur | F63: per week
C65: Position | D65: Driver | E65: =PROPER(D65) -> Driver

Sheet FillIn
A1: Inhoud
C2: De ondertekende:
C3: Krachten: | D3: =VLOOKUP($D$4,Employee!$A$3:$T$37,1,false) -> dhr. G. Aslan | G3: Werkgever: | H3: DeNeX Uitzendbureau B.V. | M3: =IF(VLOOKUP($D$4,Employee!$A$3:$T$37,2,false)="de heer","heer","mevrouw") -> heer | N3: =VLOOKUP($D$4,Employee!$A$3:$T$37,3,false)&" "&VLOOKUP($D$4,Employee!$A$3:$T$37,4,false) -> G. Aslan
C4: Naam: | D4: dhr. G. Aslan | G4: Bedrijfsnaam: | H4: =VLOOKUP($H$3,CRM,1,TRUE) -> DeNeX Uitzendbureau B.V. | M4: =VLOOKUP($D$4,Employee!$A$3:$T$37,2,false)&" "&VLOOKUP($D$4,Employee!$A$3:$T$37,3,false)&" "&VLOOKUP($D$4,Employee!$A$3:$T$37,4,false) -> de heer G. Aslan | O4: =VLOOKUP($D$4,Employee!$A$3:$T$37,4,false)&", "&VLOOKUP($D$4,Employee!$A$3:$T$37,3,false) -> Aslan, G.
C5: Adres: | D5: =VLOOKUP($D$4,Employee!$A$3:$T$37,5,false) -> Bikscotelaan 248 /2/2140 Borgerhout | G5: Naam: | H5: =VLOOKUP($H$3,CRM,13,TRUE)&" "&VLOOKUP($H$3,CRM,3,TRUE)&" "&VLOOKUP($H$3,CRM,15,TRUE) -> Hr. D.O. Ibryam | M5: =IF(VLOOKUP($H$3,CRM,13,TRUE)="Mw.","mevrouw ","de heer ")&VLOOKUP($H$3,CRM,3,TRUE)&" "&VLOOKUP($H$3,CRM,15,TRUE) -> de heer D.O. Ibryam | N5: =IF(VLOOKUP($H$3,CRM,13,TRUE)="Mw.","mevrouw ","heer ")&VLOOKUP($H$3,CRM,3,TRUE)&" "&VLOOKUP($H$3,CRM,15,TRUE) -> heer D.O. Ibryam
C6: Postcode: | D6: =LEFT(VLOOKUP($D$4,Employee!$A$3:$T$37,6,false),7) -> 2140 An | G6: Adres: | H6: =VLOOKUP($H$3,CRM,6,TRUE) -> Gebroken Meeldijk 66, Unit 1.15
C7: Plaats: | D7: =TRIM(MID(VLOOKUP($D$4,Employee!$A$3:$T$37,6,FALSE),8,LEN(VLOOKUP($D$4,Employee!$A$3:$T$37,6,FALSE)))) -> twerp | G7: Postcode: | H7: =VLOOKUP($H$3,CRM,8,TRUE) -> 2991 VD
C8: Geb.datum: | D8: =VLOOKUP($D$4,Employee!$A$3:$T$37,13,false) -> 29310 | G8: Plaats: | H8: =VLOOKUP($H$3,CRM,7,TRUE) -> Barendrecht
C9: BSN: | D9: =VLOOKUP($D$4,Employee!$A$3:$T$37,11,false) -> 235116026 | G9: Telefoon: | H9: =VLOOKUP($H$3,CRM,9,TRUE) -> +31628813127 | M9: =VLOOKUP($H$3,CRM,11,TRUE) -> NL
G10: BTW Nummer: | H10: =VLOOKUP($H$3,CRM,12,TRUE) -> NL863179344B01
C11: In dienst van | D11: =VLOOKUP($D$4,Employee!$A$3:$T$37,14,false) -> 45979 | G11: KvK Nummer: | H11: =VLOOKUP($H$3,CRM,10,TRUE) -> 84349735
C12: Dienst tot | D12: =VLOOKUP($D$4,Employee!$A$3:$T$37,16,false) -> 46159
C13: Functie | D13: =VLOOKUP($D$4,Employee!$A$3:$T$37,20,false) -> Chauffeur
C14: Proeftijd | D14: =VLOOKUP($D$4,Employee!$A$3:$T$37,17,false) | F14: =EDATE(D11,VALUE(LEFT(D14,2))) -> 45979 | G14: Transportmanager: | H14: Intern
C15: Arbeidsduur | D15: =VLOOKUP($D$4,Employee!$A$3:$T$37,19,false) -> 40 uur per week | G15: Aantal voertuig(en) | H15: 6
C16: Weekplanning | D16: maandag t/m vrijdag | G16: Uur per week: | H16: 40
C17: Werktijden | D17: tussen 7:00 uur t/m 19:00 uur
C18: Opzegtermijn: | D18: 1 maand
C19: Vergoeding: | D19: 350 | E19: per mnd | G19: Vergoeding incl. BTW: | H19: 423.5 | I19: per mnd
C21: Loonschaal | D21: =VLOOKUP($G$21,Schalen25,2,TRUE) -> D | G21: D 5
C22: Trede | D22: =VLOOKUP($G$21,Schalen25,3,TRUE) -> 5 | G22: Weekloon: | H22: =VLOOKUP($G$21,Schalen25,4,TRUE) -> 748.58
C23: Uurloon 100% | D23: =VLOOKUP($G$21,Schalen25,7,TRUE) -> 18.71 | G23: Loon 4 weken: | H23: =VLOOKUP($G$21,Schalen25,5,TRUE) -> 2994.32
C24: Afwijkende loon: | D24: =D23 -> 18.71
C25: Reiskosten | D25: 0.23 | G25: Loon maand: | H25: =VLOOKUP($G$21,Schalen25,6,TRUE) -> 3254.83
C26: Max.reiskosten | D26: 100 | G26: Uurloon 130% | H26: =VLOOKUP($G$21,Schalen25,8,TRUE) -> 24.32
G27: Uurloon 150% | H27: =VLOOKUP($G$21,Schalen25,9,TRUE) -> 28.07
C28: Plaats | D28: Rijswijk
C29: Datum | D29: =D11-1 -> 45978
G30: Leeftijd: | H30: =YEAR(NOW())-YEAR(D8) -> 45 | I30: =LOOKUP($H$30,Mins,Vakantie!A2:A9) -> 5
C31: CAO (niet in te vullen) | G31: 39 | H31: 3
C32: Vakantie leeftijd | D32: =LOOKUP(H30,Mins,Leeftijd) -> 45 t/m 49 jaar | G32: 19 t/m 39 jaar | H32: 19 t/m 39 jaar | M32: =LOOKUP(H30,Mins,Vakantie!A2:A9) -> 5
C33: Vacantiedagen | D33: =VLOOKUP(I30,Vakantie,5,true) -> 25 dagen | G33: Onbetaald verlof:
C34: ATV | D34: 3.5 | G34: Aantal dagen: | H34: =NETWORKDAYS(H36,H37) -> 129
C35: Vakantiebijslag | D35: 0.08 | G35: Dagen/Uren: | H35: dagen
G36: Begin datum: | H36: 45979 | M36: =DATEDIF(D11, D29, "M") -> #NUM!
C37: Annex | G37: Eind datum: | H37: 46159
C38: Datum: | D38: 45963
C39: functiewijziging: | G39: Uitzendkracht:
C40: Functie en Schaal: | G40: Contractduur: | H40: =VLOOKUP($D$4,Employee!A3:O37,15,false) -> 6 maanden | I40: 7
C41: Arbeidsduur: | G41: Einddatum: | H41: =EDATE(D11-1,I40) -> 46190
C42: Uur per week
C43: Werktijden | G43: vakantiedagen | H43: 0.1092
C44: Werkdagen: | D44: za zo | G44: vakantietoeslag | H44: 0.0833
C45: Werktijden van: | D45: 0.29166667
C46: Werktijden tot: | D46: 0.79166667 | G46: ZZP
C47: functiegroep | G47: A.A. Kazakov
C48: Functiegroep: | D48: =VLOOKUP($G$21,Schalen25,2,TRUE) -> D | G48: Adres: | H48: =VLOOKUP($G$47,CRM,6,FALSE) -> Loosduinseweg 867
C49: FunctieJaar: | D49: =VLOOKUP($G$21,Schalen25,3,TRUE) -> 5 | G49: Postcode/Plaats: | H49: =VLOOKUP($G$47,CRM,8,FALSE) -> 2571AV | I49: =VLOOKUP($G$47,CRM,7,FALSE) -> s-Gravenhage
C50: Ondertekening | G50: Contact: | H50: =VLOOKUP($G$47,CRM,13,TRUE)&" "&VLOOKUP($G$47,CRM,3,TRUE)&" "&VLOOKUP($G$47,CRM,15,TRUE) -> Hr. A.A. Kazakov | M50: =IF(VLOOKUP($G$47,CRM,13,TRUE)="Mw.","mevrouw ","deheer ")&VLOOKUP($G$47,CRM,3,TRUE)&" "&VLOOKUP($G$47,CRM,15,TRUE) -> deheer A.A. Kazakov
C51: Plaats: | D51: =H8 -> Barendrecht | G51: KvK: | H51: =VLOOKUP($G$47,CRM,10,FALSE) -> 82225443
C52: Datum: | D52: =D11-1 -> 45978 | G52: Factureren: | H52: Aan het eind van de gewerkte week.
F53: 28 | H53: Winkeldistributie
F54: 26 | H54: Depod
G55: Aanvang | H55: 45960

Sheet Employee
A2: Name | B2: Salutation | C2: Initials | D2: Last Name | E2: Address/Street | F2: Postal Code/City | G2: Country | H2: Telephone | I2: Email | J2: KIWA | K2: BSN | L2: Bank account | M2: Date of birth | N2: Employment date | O2: Contract duration | P2: ContractEndDate | Q2: Probationary period | R2: Hourly wage | S2: Working hours | T2: Position
A3: dhr. G. Boeru | B3: de heer | C3: G. | D3: Boeru | E3: Str.Lanternie Nr.92 | F3: 023095 Bucuresti | G3: ROMANIA | H3: 31616032687 | I3: boerugabi@yahoo.com | J3: 45964 | K3: 447266925 | L3: NL54INGB0105640972 | M3: 27324 | N3: 45964 | O3: 6 maanden | P3: 46144 | R3: 18.71 | S3: 40 uur per week | T3: Chauffeur
A4: dhr. R. Tataru | B4: de heer | C4: R. | D4: Tataru | E4: Str.Grainitei Nr.27 Bl.S2 Sc.B Ap.2 | F4: 705200 Pascani | G4: ROMANIA | H4: 40756724384 | I4: rabert_tataru88@yahoo.com | J4: 45964 | K4: 292515121 | M4: 32206 | N4: 45964 | O4: 6 maanden | P4: 46144 | R4: 18.71 | S4: 40 uur per week | T4: Chauffeur
A5: dhr. I. Gyurov | B5: de heer | C5: I. | D5: Gyurov | E5: Str.Blagoy Gebrev 58/43 | G5: BULGARIJE | H5: 359899705392 | I5: Ivan.v.gyurov@gmail.com | M5: 30033 | N5: 45964 | O5: 6 maanden | P5: 46144 | R5: 18.71 | S5: 40 uur per week | T5: Chauffeur
A6: dhr. R. Stiac | B6: de heer | C6: R. | D6: Stiac | E6: Ale.Trandafirilor,2A Bl.1 Sc.B,Et.5,Ap.503 Oradea | G6: ROMANIA | H6: 0040 775 309 576 | I6: razvanstiac@yahoo.com | J6: 45966 | K6: 424099536 | L6: RO44BRDE0505V1117399050 | M6: 30283 | N6: 45966 | O6: 6 maanden | P6: 46177 | R6: 18.71 | S6: 40 uur per week | T6: Chauffeur
A7: dhr. D.I. Bejan | B7: de heer | C7: D.I. | D7: Bejan | E7: Sat.Stroiesti | F7: 717226 Botasani | G7: ROMANIA | H7: 31623057192 | I7: bejan.olani20@gmail.com | J7: 45971 | K7: 336659520 | L7: NL64INGB0102322422 | M7: 34413 | N7: 45971 | O7: 6 maanden | P7: 46152 | R7: 18.71 | S7: 40 uur per week | T7: Chauffeur
A8: dhr. G. Aslan | B8: de heer | C8: G. | D8: Aslan | E8: Bikscotelaan 248 /2/2140 Borgerhout | F8: 2140 Antwerp | G8: BELGIUM | H8: 0032 483120970 | I8: gorkanaslan@hotmail.com | J8: 45979 | K8: 235116026 | L8: BE58143105213779 | M8: 29310 | N8: 45979 | O8: 6 maanden | P8: 46159 | R8: 18.71 | S8: 40 uur per week | T8: Chauffeur

Sheet ZZP
B1: OVEREENKOMST VAN OPDRACHT
B3: De ondergetekenden:
B4: Opdrachtgever: | F4: Opdrachtnemer:
B5: Bedrijfsnaam | C5: : | D5: =FillIn!H4 -> DeNeX Uitzendbureau B.V. | F5: Bedrijfsnaam | G5: : | H5: =FillIn!G47 -> A.A. Kazakov
B6: Adres | C6: : | D6: =FillIn!H6 -> Gebroken Meeldijk 66, Unit 1.15 | F6: Adres | G6: : | H6: =FillIn!H48 -> Loosduinseweg 867
B7: Postcode/Plaats | C7: : | D7: =FillIn!H7&" "&FillIn!H8 -> 2991 VD Barendrecht | F7: Postcode/Plaats | G7: : | H7: =FillIn!H49&" "&FillIn!I49 -> 2571AV s-Gravenhage
B8: Contact | C8: : | D8: =FillIn!M5 -> de heer D.O. Ibryam | F8: Contact | G8: : | H8: =FillIn!M50 -> deheer A.A. Kazakov
B10: OVERWEGENDE DAT:
B12: de Opdrachtnemer door de Opdrachtgever is benaderd om de nader te noemen werkzaamheden te verrichten, en de Opdrachtnemer in staat en bereid is deze werkzaamheden te verrichten;
B14: de Partijen overeen zijn gekomen zich uitsluitend te verbinden op basis van een overeenkomst van Opdracht in de zin van artikel 7:400 BW en aanverwante wetgeving;
B16: de Partijen uitdrukkelijk overeenkomen geen arbeidsovereenkomst aan te gaan in de zin van artikel 7:610 BW en aanverwante wetgeving;
B18: de Partijen zijn overeengekomen alle afspraken met betrekking tot de Opdracht in deze overeenkomst vast te leggen.
B20: KOMEN ALS VOLGT OVEREEN:
B22: Artikel 1: DE OPDRACHT
B23: De Opdrachtnemer zal voor de Opdrachtgever gedurende de duur van de overeenkomst de volgende werkzaamheden verrichten (de "Opdracht"):
B24: Opdrachtnemer verricht diensten als zijnde: | E24: Vrachtwagenchauffeur
B26: Artikel 2: UITVOERING VAN DE OPDRACHT
B27: De Opdrachtnemer zal bij zijn werkzaamheden de normen van een goede Opdrachtnemer in acht houden en aanvaardt de volledige verantwoordelijkheid de Opdracht op een juiste wijze uit te voeren.
B29: Ingeval de Opdrachtnemer op een bepaald tijdstip verwacht dat hij de Opdracht niet of niet naar behoren kan uitvoeren, dient de Opdrachtnemer de Opdrachtgever hiervan onverwijld op de hoogte te brengen. De Partijen treden alsdan in overleg over mogelijke aanpassingen.
B31: De Opdrachtnemer voert de werkzaamheden met betrekking tot de Opdracht zelfstandig en naar eigen inzicht uit. De Opdrachtgever kan aanwijzingen geven met betrekking tot de uitvoering van de Opdracht.
B33: De Opdrachtgever dient de Opdrachtnemer alle benodigde informatie en zaken ten behoeve van de Opdracht te verstrekken.
B34: De Opdrachtgever is verantwoordelijk en aansprakelijk voor schade die voorkomt uit foutief of onjuist verstrekte informatie of zaken.
B36: Artikel 3: UITBESTEDING AAN DERDEN
B37: De Opdrachtnemer is gerechtigd de Opdracht gedeeltelijk of geheel uit te besteden aan derden.
B39: Artikel 4: VERVANGING
B40: De Opdrachtnemer is in geval van verhindering vrij vervanging aan te wijzen voor de werkzaamheden; De Opdrachtnemer stelt de Opdrachtgever tijdig op de hoogte indien hij verhinderd is in het uitvoeren van de overeenkomst.
B42: Artikel 5: DUUR
B43: De overeenkomst vangt aan op 29 september 2025 voor een onbepaalde duur.
... B46: Ter zake van de uitvoering van de Opdracht zal de Opdrachtnemer van de Opdrachtgever de volgende vergoeding ontvangen:
B47: 28 | C47: euro per gewerkt uur Winkeldistributie
B48: 26 | C48: euro per gewerkt uur Depod
B50: De Opdrachtnemer zal een factuur zenden of doen zenden aan de Opdrachtgever voor de verrichte werkzaamheden. De
B51: factuur zal in ieder geval voldoen aan de wettelijke vereisten en zal worden verzonden op het volgende moment:
B52: Aan het eind van de gewerkte week.
B54: De Opdrachtgever betaalt de factuur zodra de factuur welke door de Opdrachtgever naar de transporteur is verzonden,
B55: is voldaan aan de Opdrachtgever.
B57: De Opdrachtnemer is verantwoordelijk voor alle overige kosten die redelijkerwijs gemaakt worden ten behoeve van de
B58: uitvoering van de Opdracht. De overige kosten kunnen niet verhaald worden op de Opdrachtgever.
B60: Artikel 7: INTELLECTUELE EIGENDOM
B61: De Opdrachtgever behoudt alle intellectuele eigendomsrechten op informatie of zaken die door de Opdrachtgever aan de
B62: Opdrachtnemer worden verstrekt ter uitvoering van de Opdracht. De Opdrachtnemer mag deze informatie of zaken niet
B63: kopiëren, verstrekken aan derden of op een andere wijze gebruiken, anders dan ter uitvoering van de Opdracht.
B65: Het eigendom van het uit hoofde van de Opdracht tot stand gekomen werk komt toe aan de Opdrachtnemer.
... B143: Aldus overeengekomen en in tweevoud opgemaakt en ondertekend:
B145: Plaats | C145: : | D145: =FillIn!H8 -> Barendrecht | F145: Datum | G145: : | H145: =FillIn!H55-1 -> 45959
B150: (Handtekening Opdrachtgever) | F150: (Handtekening Opdrachtnemer)
B151: =FillIn!M5 -> de heer D.O. Ibryam | F151: =FillIn!M50 -> deheer A.A. Kazakov

Sheet Reglement
B1: INTERN REGLEMENT VOOR CHAUFFEURS
B3: Artikel 1: Algemeen
B4: Dit reglement is van toepassing op alle chauffeurs die werkzaamheden verrichten voor het bedrijf, zowel in dienstverband
B5: als ZZP. Het naleven van deze regels is verplicht. Overtredingen kunnen leiden tot sancties, inhoudingen of beëindiging
B6: van samenwerking.
B8: Artikel 2: Documenten en voertuigcontrole
B9: 1. De chauffeur is verantwoordelijk voor het controleren van alle benodigde voertuigdocumenten vóór vertrek:
B10: ■ Verzekering
B11: ■ NIWO-vergunning
B12: ■ Kentekenbewijs
B13: ■ APK
B14: 2. Het voertuig mag niet worden gebruikt als bovenstaande documenten ontbreken.
... B92: Gebruik correcte routes volgens opdrachtgevers:
B93: ■ AH routes: | D93: https://dc-routes.nl/
B94: ■ JUMBO routes: | D94: https://routeboek-prd-we-driver.azurewebsites.net/
B95: ■ PLUS routes: | D95: https://www.werkenbijplus.nl/PlusRoutes/StoreList.aspx
B96: Afwijken van route = verantwoordelijkheid van chauffeur.
B98: Artikel 17: Regels voor ZZP-chauffeurs
B99: 1. Betaling vindt plaats op woensdag.
B100: 2. Uren moeten uiterlijk dinsdag zijn ingediend. Te laat = uitbetaling week later.
B101: 3. Bij vertrek of einde samenwerking wordt één factuur 6 weken vastgehouden i.v.m. boetes.
B102: 4. Bij problemen met betaling van Braven: eerst zelf contact opnemen, daarna assistentie mogelijk.
B104: Artikel 18: ONDERTEKENING
B105: Aldus overeengekomen en in tweevoud opgemaakt en ondertekend:
B107: Datum | C107: : | D107: =FillIn!D52 -> 45978
B112: (Handtekening Opdrachtnemer)
B113: =FillIn!M4 -> de heer G. Aslan

Sheet Правилник
B1: DENIS EXPRESS B.V. - ВЪТРЕШЕН ПРАВИЛНИК ЗА ШОФЬОРИ
B3: Тези разпоредби се отнасят за всички шофьори, работещи за компанията, както наети, така и самонаети.
B4: Настоящият правилник съдържа задължителни инструкции за безопасна, коректна и професионална работа на всички
B5: шофьори. Спазването на правилата е задължително. Неспазването води до санкции и дисциплинарни последици.
B7: 1. Документи и задължения преди тръгване
B8: Всеки шофьор е длъжен преди започване на курса да извърши проверка на автомобила и документите.
B9: Задължително се проверяват и носят:
B10: ● Verzekering (застраховка)
B11: ● Лиценз NIWO
B12: ● Kentekenbewijs (талон)
B13: ● APK (технически преглед)
B14: ● Лична шофьорска карта
... B101: 12. Маршрути
B102: AH Route: | D102: https://dc-routes.nl/
B103: JUMBO Route: | D103: https://routeboek-prd-we-driver.azurewebsites.net/
B104: PLUS Route: | D104: https://www.werkenbijplus.nl/PlusRoutes/StoreList.aspx
B106: 13. Санкции и финансова отговорност
B107: Нарушаването на правилника води до дисциплинарни и или финансови санкции според тежестта на нарушението
B109: Дисциплинарни мерки
B110: ● устно предупреждение
B111: ● писмено предупреждение
B112: ● временно отстраняване от работа
B113: ● прекратяване на договора или сътрудничеството
B115: Финансова отговорност (глоби и удръжки)
B116: Нарушение | H116: Санкция
B117: неспазено предизвестие при напускане | H117: 1500 евро
B118: Eigen risico при щета (самоучастие) | H118: 1500 евро
B119: оронване престижа на фирмата (скандали с клиенти, непристойно поведение, | H119: 2500 евро
B120: агресия, обиди)
B121: оставяне на горивна карта или тахо карта в камиона | H121: 150 евро
B122: загубен ключ, бадж или горивна карта | H122: 250 евро
B123: неправилно използване на Rema кабел водещо до късо съединение | H123: пълна стойност на ремонта
B124: подаване на ток с ABS кабел | H124: пълна стойност на ремонта
B125: оставено ремарке без заключване или без гориво | H125: 250 евро
B126: непредадени документи като dagstaten и листи | H126: 50 евро на ден
B127: неспазване на маршрут или загуба на товар | H127: пълна отговорност
B128: глоби от полиция и институции за скорост, тахограф и други са за сметка на шофьора
B130: 14. Потвърждение
B131: С подписа си удостоверявам, че съм запознат или запозната с правилника и се задължавам да го спазвам
B133: Така договорено, съставено и подписано в два екземпляра:
B135: Datum | C135: : | D135: =FillIn!D52 -> 45978
B140: (Подпис Изпълнител)
B141: =FillIn!M4 -> de heer G. Aslan

Sheet Regulations
B1: DENIS EXPRESS B.V. – INTERNAL DRIVER REGULATIONS
B3: These provisions apply to all drivers working for the company, both employees and self-employed contractors.
B4: This regulation contains mandatory instructions for the safe, correct, and professional performance of all drivers’ duties.
B5: Compliance with these rules is obligatory. Non-compliance will result in disciplinary and/or financial sanctions.
B7: 1. Documents and Obligations Before Departure
B8: Every driver must check the vehicle and required documents before starting a route.
B9: The following must be verified and carried:
B10: ● Insurance (Verzekering)
B11: ● NIWO Licence
B12: ● Registration Certificate (Kentekenbewijs)
B13: ● APK (Technical Inspection Certificate)
B14: ● Driver licence
... B101: 12. Маршрути
B102: AH Route: | D102: https://dc-routes.nl/
B103: JUMBO Route: | D103: https://routeboek-prd-we-driver.azurewebsites.net/
B104: PLUS Route: | D104: https://www.werkenbijplus.nl/PlusRoutes/StoreList.aspx
B106: 13. Sanctions and Financial Responsibility
B107: Violation of these regulations may lead to disciplinary and/or financial sanctions depending on the severity.
B109: Disciplinary measures:
B110: ● Verbal warning
B111: ● Written warning
B112: ● Temporary suspension
B113: ● Termination of employment or cooperation
B115: Financial liability (fines and deductions):
B116: Violation | H116: Penalty
B117: Leaving employment without notice | H117: 1500 евро
B118: Insurance deductible for damages (Eigen risico) | H118: 1500 евро
B119: Damage to company reputation (misconduct, client conflicts, aggression, offensive behaviour) | H119: 2500 евро
B120: Leaving a fuel or tachograph card in the truck | H120: 150 евро
B121: Lost key, badge, or fuel card | H121: 250 евро
B122: Incorrect use of Rema cable causing a short circuit | H122: Full repair cost
B123: Using ABS cable for jump-starting | H123: Full repair cost
B124: Leaving trailer unlocked or without fuel | H124: 250 евро
B125: Failure to submit daily registers or documents | H125: 50 евро на ден
B126: Route violation or loss of load | H126: Full liability
B127: Fines from police or authorities (speeding, tachograph, etc.) | H127: Paid by driver
B129: 14. Acknowledgement
B130: By signing below, I confirm that I have read and understood these regulations and agree to comply with them.
B132: Signed in duplicate on:
B134: Date | C134: : | D134: =FillIn!D52 -> 45978
B139: Driver’s Signature
B140: =FillIn!M4 -> de heer G. Aslan

Sheet Termination
B1: BEËINDIGING ARBEIDSOVEREENKOMST
I3: =FillIn!H4 -> DeNeX Uitzendbureau B.V.
I4: =FillIn!H6 -> Gebroken Meeldijk 66, Unit 1.15
I5: =FillIn!H7&" "&FillIn!H8 -> 2991 VD Barendrecht
B7: ="Aan: "&FillIn!D4 -> Aan: dhr. G. Aslan
B8: =FillIn!D5 -> Bikscotelaan 248 /2/2140 Borgerhout
B9: =FillIn!D6&" "&FillIn!D7 -> 2140 An twerp
B12: Datum: | C12: =FillIn!H8&", "&TEXT(FillIn!D38,"dd mmmm YYYY") -> Barendrecht, 02 november 2025
B13: Betreft: | C13: Beëindiging Arbeidsovereenkomst
B17: ="Geachte "&FillIn!M3&" "&FillIn!N3&"," -> Geachte heer G. Aslan,
B19: ="Hierbij delen wij u mede, dat uw arbeidsovereenkomst per "&IF(FillIn!D12>FillIn!F14,TEXT(FillIn!D12,"dd mmmm yyyy")," tijdens proeftijd "&TEXT(FillIn!D12,"dd mmmm yyyy"))&" wordt beëindigd. U heeft bij ons bedrijf vanaf "&TEXT(FillIn!D11,"dd mmmm yyyy")&" tot en met "&TEXT(FillIn!D12,"dd mmmm yyyy")&"." -> Hierbij delen wij u mede, dat uw arbeidsovereenkomst per 17 mei 2026 wordt beëindigd. U heeft bij ons bedrijf vanaf 18 november 2025 tot en met 17 mei 2026.
B21: Wij bedanken u voor uw inzet en wensen u veel succes voor het vinden van een nieuwe baan.
B22: Hopende u hierbij voldoende te hebben geïnformeerd.
B24: Met vriendelijke groet,
B30: =FillIn!M5 -> de heer D.O. Ibryam

Sheet SelfT
B1: ZELF ONTSLAG
I3: =FillIn!D4 -> dhr. G. Aslan
I4: =FillIn!D5 -> Bikscotelaan 248 /2/2140 Borgerhout
I5: =FillIn!D6&" "&FillIn!D7 -> 2140 An twerp
B7: ="Aan: "&FillIn!H4 -> Aan: DeNeX Uitzendbureau B.V.
B8: =FillIn!H6 -> Gebroken Meeldijk 66, Unit 1.15
B9: =FillIn!H7&" "&FillIn!H8 -> 2991 VD Barendrecht
B12: Datum: | C12: =FillIn!H8&", "&TEXT(FillIn!D38,"dd mmmm YYYY") -> Barendrecht, 02 november 2025
B13: Betreft: | C13: Zelf ontslag
B17: ="Geachte "&FillIn!N5&"," -> Geachte heer D.O. Ibryam,
B19: ="Hierbij deel ik u mede dat ik zelf ontslag neem per "&TEXT(FillIn!D12,"dd mmmm yyyy")&". Ik zeg mijn arbeidsovereenkomst op per "&TEXT(FillIn!D12,"dd mmmm yyyy")&" en teven is dat mijn laatste werkdag bij uw bedrijf." -> Hierbij deel ik u mede dat ik zelf ontslag neem per 17 mei 2026. Ik zeg mijn arbeidsovereenkomst op per 17 mei 2026 en teven is dat mijn laatste werkdag bij uw bedrijf.
B21: Wij bedanken u voor uw inzet en wensen u veel succes voor het vinden van een nieuwe baan.
B22: Hopende u hierbij voldoende te hebben geïnformeerd.
B24: Met vriendelijke groet,
B30: =FillIn!M3&" "&FillIn!N3 -> heer G. Aslan

Sheet Unpaid
B1: BEVESTIGING ONBETAALD VERLOF
B5: ="Geachte "&FillIn!M3&" "&FillIn!N3&"," -> Geachte heer G. Aslan,
B7: ="Wij willen u graag laten weten dat uw aanvraag voor onbetaald verlof is goedgekeurd. U heeft recht op "&FillIn!H34&" "&FillIn!H35&" "&" onbetaald verlof, beginnend op "&TEXT(FillIn!H36,"dd mmmm yyyy")&" en derhalve eindigend op "&TEXT(FillIn!H37,"dd mmmm yyyy")&"." -> Wij willen u graag laten weten dat uw aanvraag voor onbetaald verlof is goedgekeurd. U heeft recht op 129 dagen onbetaald verlof, beginnend op 18 november 2025 en derhalve eindigend op 17 mei 2026.
B9: Tijdens uw verlof zult u geen werkgerelateerde taken uitvoeren. U dient de voorwaarden voor het opnemen van onbetaald verlof te volgen, zoals beschreven in ons personeelsreglement.
B11: Wij begrijpen dat deze situatie voor u belangrijk is. Wij hopen dat het verlof u de tijd en ruimte zal geven om te doen wat u nodig heeft en dat alles goed zal verlopen.
B13: Als u nog vragen heeft over het onbetaald verlof of de voorwaarden die daarvoor gelden, aarzel dan niet om contact op te nemen met onze HR-afdeling.
B15: Met vriendelijke groet,
B21: =FillIn!M5 -> de heer D.O. Ibryam

Sheet Annex
B1: Addendum arbeidsovereenkomst
B3: Ondergetekenden:
B4: Naam bedrijf: | E4: =FillIn!H4 -> DeNeX Uitzendbureau B.V.
B5: Rechtsgeldig vertegenwoordigd door: | E5: =FillIn!M5 -> de heer D.O. Ibryam
B6: Adres: | E6: =FillIn!H6 -> Gebroken Meeldijk 66, Unit 1.15
B7: Postcode en vestigingsplaats: | E7: =FillIn!H7&" "&FillIn!H8 -> 2991 VD Barendrecht
B9: Hierna te noemen: werkgever,
B11: en
B13: Naam werknemer: | E13: =FillIn!M4 -> de heer G. Aslan
B14: Adres: | E14: =FillIn!D5 -> Bikscotelaan 248 /2/2140 Borgerhout
B15: Postcode en woonplaats: | E15: =FillIn!D6&" "&FillIn!D7 -> 2140 An twerp
B16: Geboortedatum: | E16: =FillIn!D8 -> 29310
B18: Hierna te noemen: werknemer,
B20: Overwegende:
B22: - dat partijen het wenselijk achten om deze nadere afspraken schriftelijk vast te leggen in dit addendum.
B24: Verklaren hierbij te zijn overeengekomen als volgt:
B25: 1. In aanvulling en/of afwijking op de arbeidsovereenkomst komen partijen overeen dat
B27: =IF(FillIn!D40>0,"Werknemer met ingang van "&TEXT(FillIn!D38,"dd mmmm yyyy")&" is ingedeeld in functie: "&FillIn!D40&".",IF(FillIn!D42>0,"De arbeidsduur van de werknemer met ingang van "&TEXT(FillIn!D38,"dd mmmm yyyy")&" bedraagt "&FillIn!D42&" uur per week.",IF(FillIn!D45>0,"Werknemer met ingang van "&TEXT(FillIn!D38,"dd mmmm yyyy")&" werkt op de dagen "&FillIn!D44&" van "&TEXT(FillIn!D45,"hh:mm")&" tot "&TEXT(FillIn!D46,"hh:mm")&" uur.",IF(FillIn!D48>0,"Werknemer met ingang van "&TEXT(FillIn!D38,"dd mmmm yyyy")&" is ingedeeld in functiegroep: "&FillIn!D48&" met functiejaar "&FillIn!D49&"."," - ")))) -> Werknemer met ingang van 02 november 2025 werkt op de dagen za zo van 07:00 tot 19:00 uur.
B29: 2. Dit addendum zal aan de geldende arbeidsovereenkomst worden gehecht en maakt - na ondertekening onlosmakelijk onderdeel uit van de arbeidsovereenkomst.
B30: 3. De overige bepalingen, zoals opgenomen in de arbeidsovereenkomst, blijven onverkort van toepassing.
B32: ="Aldus overeengekomen en in tweevoud opgemaakt te "&FillIn!H8&" op "&TEXT(FillIn!D38-3,"dd mmmm yyyy")&"." -> Aldus overeengekomen en in tweevoud opgemaakt te Barendrecht op 30 oktober 2025.
B34: ="Namens werkgever "&FillIn!H4 -> Namens werkgever DeNeX Uitzendbureau B.V. | H34: Werknemer
B39: ___________________ | H39: _________________
B40: =FillIn!M5 -> de heer D.O. Ibryam | H40: =FillIn!M4 -> de heer G. Aslan

Sheet AgrTM
B2: Vervoermanagement overeenkomst
B4: De ondergetekenden:
B6: ="1. "&FillIn!H4&", gevestigd aan de "&FillIn!H6&", "&FillIn!H7&" "&FillIn!H8&", rechtsgeldig vertegenwoordigd door haar directeur, "&FillIn!M5&", hierna te noemen Opdrachtgever oftewel de transportonderneming," -> 1. DeNeX Uitzendbureau B.V., gevestigd aan de Gebroken Meeldijk 66, Unit 1.15, 2991 VD Barendrecht, rechtsgeldig vertegenwoordigd door haar directeur, de heer D.O. Ibryam, hierna te noemen Opdrachtgever oftewel de transportonderneming,
B8: en
B10: ="2. "&FillIn!M4&IF(FillIn!H14="Intern",", woonachtig",", hodn "&FillIn!G47&", kantoor houdende")&" aan de "&FillIn!D5&", "&FillIn!D6&" "&FillIn!D7&", hierna te noemen "&IF(FillIn!H14="Intern","Werknemer ","externe Opdrachtnemer ")&" oftewel vervoersmanager,""" -> 2. de heer G. Aslan, woonachtig aan de Bikscotelaan 248 /2/2140 Borgerhout, 2140 An twerp, hierna te noemen Werknemer oftewel vervoersmanager,"
B12: komen overeen als volgt:
B14: Artikel 1
B16: ="a. Vervoermanager zal per "&TEXT(FillIn!D11,"dd mmmm yyyy")&IF(FillIn!D12>0," tot en met "&TEXT(FillIn!D12,"dd mmmm yyyy"),"")&" in opdracht van opdrachtgever het management voeren over de onderneming." -> a. Vervoermanager zal per 18 november 2025 tot en met 17 mei 2026 in opdracht van opdrachtgever het management voeren over de onderneming.
B18: b. Onder het voeren van management wordt verstaan het leidinggeven aan de vervoersactiviteiten in de meest ruime zin van het woord.
B20: Het takenpakket betreft onder meer, maar is niet beperkt tot, de volgende werkzaamheden:
B21: - Aanschaf en beheer materieel;
B22: - Calculatie en vaststelling vrachtprijs;
B23: - Werkverdeling;
B24: - Debiteuren/crediteurenbewaking;
B25: - Aanname/ontslag personeel;
B26: - Klachtenafhandeling.
B28: Artikel 2
B30: ="a. Deze overeenkomst is aangegaan voor "&IF(FillIn!D12>0,"bepaalde ","onbepaalde ")&"tijd. Elk van partijen kan de overeenkomst opzeggen met inachtneming van een opzegtermijn van "&FillIn!D18&"." -> a. Deze overeenkomst is aangegaan voor bepaalde tijd. Elk van partijen kan de overeenkomst opzeggen met inachtneming van een opzegtermijn van 1 maand.
B32: b. De opzegging dient schriftelijk te geschieden.
B34: c. Ieder van partijen is gerechtigd deze overeenkomst met onmiddellijke ingang, zonder ingebrekestelling of gerechtelijke tussenkomst, op te zeggen indien:
B36: - Opdrachtgever of de Vervoersmanager surseance van betaling aanvraagt, in faillissement treedt of in liquidatie treedt;
B37: - Opdrachtgever of de Vervoersmanager of diens werknemer(s) die betrokken zijn bij de uitvoering van deze overeenkomst strafrechtelijk wordt/worden vervolgd;
B38: - de zeggenschap over opdrachtgever of de Vervoersmanager wijzigt als gevolg van aandeelhouderswisselingen.
B42: Artikel 3
B44: ="De managementvergoeding is € "&FillIn!D19&" per maand, gebaseerd op "&FillIn!H15&" voertuig(en). De totale vergoeding die opdrachtgever aan de vervoermanager verschuldigd is bedraagt € "&IF(FillIn!H14="Intern",FillIn!D19&" - euro per maand. ",FillIn!H19&" - euro per maand, inclusief omzetbelasting. ")&" De managementvergoeding wordt maandelijks voldaan. De vergoeding zal jaarlijks kunnen worden herzien. Partijen zullen omtrent een eventuele herziening overleg plegen. In totaal zal de vervoermanager "&FillIn!H16&" uur per week voor opdrachtgever werkzaamheden verrichten." -> De managementvergoeding is € 350 per maand, gebaseerd op 6 voertuig(en). De totale vergoeding die opdrachtgever aan de vervoermanager verschuldigd is bedraagt € 350 - euro per maand. De managementvergoeding wordt maandelijks voldaan. De vergoeding zal jaarlijks kunnen worden herzien. Partijen zullen omtrent een eventuele herziening overleg plegen. In totaal zal de vervoermanager 40 uur per week voor opdrachtgever werkzaamheden verrichten.
B46: Partijen hebben zich ervan vergewist dat heffing van loonbelasting en werknemersverzekeringspremies ter zake van de uit te betalen managementvergoeding achterwege kan blijven.
B48: Artikel 4
B50: De Vervoersmanager verplicht zich alles te doen c.q. na te laten wat een goed manager behoort te doen c.q. na te laten, en zich volledig in te zetten om de belangen van opdrachtgever te bevorderen.
B52: Artikel 5
B54: Opdrachtgever zal de Vervoersmanager vrijwaren voor eventuele aanspraken van derden voor zover die aanspraken betrekking hebben op of verband houden met de werkzaamheden die de Vervoersmanager binnen de onderneming van opdrachtgever vervult of heeft vervuld.
B56: Artikel 6
B58: De Vervoersmanager is verplicht tot volstrekte geheimhouding, ook na het einde van deze overeenkomst, van al hetgeen hem uit hoofde van zijn functie binnen de onderneming van opdrachtgever in de ruimste zin bekend is of zal worden, voor zover door de bekendmaking van die wetenschap de belangen van opdrachtgever kunnen worden geschaad.
B60: ="Aldus overeengekomen, opgemaakt in tweevoud en getekend te "&FillIn!H8&" op "&TEXT(FillIn!D52,"dd mmmm yyyy")&"." -> Aldus overeengekomen, opgemaakt in tweevoud en getekend te Barendrecht op 17 november 2025.
B62: Opdrachtgever | H62: De Vervoersmanager
B67: ………………………….. | H67: …………………………..
B68: =FillIn!M5 -> de heer D.O. Ibryam | H68: =FillIn!M50 -> deheer A.A. Kazakov

Sheet AgrLoan
B1: Inleenovereenkomst
B3: De Uitlener / Uitzendonderneming
B5: Naam | F5: =FillIn!H4 -> DeNeX Uitzendbureau B.V.
B6: Adres | F6: =FillIn!H6&", "&FillIn!H7&" "&FillIn!H8 -> Gebroken Meeldijk 66, Unit 1.15, 2991 VD Barendrecht
B7: Contactpersoon | F7: =FillIn!M5 -> de heer D.O. Ibryam
B8: BTW nummer | F8: =FillIn!H10 -> NL863179344B01
B9: KvK Nummer | F9: =FillIn!H11 -> 84349735
B10: E-mail | F10: =VLOOKUP(FillIn!H3,CRM,14,TRUE) -> info@denexuitzendbureau.nl
B11: Telefoon | F11: =FillIn!H9 -> +31628813127
B13: en
B15: De Inlener / Transport Onderneming
B17: Naam | F17: =FillIn!G47 -> A.A. Kazakov
B18: Adres | F18: =FillIn!H48&", "&FillIn!H49&" "&FillIn!I49 -> Loosduinseweg 867, 2571AV s-Gravenhage
B19: Contactpersoon | F19: =FillIn!M50 -> deheer A.A. Kazakov
B20: BTW nummer | F20: =VLOOKUP(FillIn!$G$47,CRM,12,TRUE) -> NL003657916B47
B21: KvK Nummer | F21: =FillIn!$H$51 -> 82225443
B22: E-mail | F22: =VLOOKUP(FillIn!G47,CRM,14,TRUE) -> kazakovasen5@gmail.com
B23: Telefoon | F23: =VLOOKUP(FillIn!G47,CRM,9,TRUE) -> 0685411440
B25: in aanmerking nemende:
B27: ● | C27: dat Inlener een transportonderneming exploiteert;
B28: ● | C28: dat Uitlener een instelling als bedoeld in artikel 13 lid 2 sub b Regeling Wegvervoer Goederen exploiteert;
B29: ● | C29: dat Inlener in dat kader nu en in de toekomst mogelijk overeenkomsten wenst aan te gaan met Uitlener, bestaande uit het door Uitlener aan Inlener ter beschikking stellen van zelfstandige chauffeurs;
B30: ● | C30: dat Uitlener bereid is opdrachten aan te nemen en uit te voeren ten behoeve van het bedrijf van Inlener;
B31: ● | C31: dat Partijen overeen zijn gekomen zich uitsluitend te verbinden op basis van een overeenkomst van opdracht in de zin van artikel 7:400 BW en aanverwante wetgeving;
B32: ● | C32: dat Partijen uitdrukkelijk overeenkomen geen arbeidsovereenkomst aan te gaan in de zin van artikel 7:610 BW en aanverwante wetgeving;
B33: ● | C33: dat partijen de afspraken die steeds van toepassing zullen zijn bij (de uitvoering van) deze overeenkomst(en) willen vastleggen in deze overeenkomst, welke gezien dient te warden als raamovereenkomst voor de huidige en toekomstige overeenkomst( en).
B35: De individuele overeenkomsten die tot stand komen tussen Inlener en Uitlener en de lopende overeenkomst(en) zullen steeds worden beheerst door de volgende voorwaarden:
B37: 1. Toepassing van de Juiste Arbeidsvoorwaarden door de Uitlener
B39: Deze raamovereenkomst met bijlagen is steeds van toepassing op alle door partijen nader te sluiten overeenkomsten terzake het door Uitlener aan Inlener beschikbaar stellen van chauffeurs, ook zonder enige verwijzing daarnaar in de door Inlener geplaatste opdrachten c.q. de eventueel door Uitlener verstrekte opdrachtbevestigingen.
B41: De Uitlener is verantwoordelijk voor het toepassen van de juiste arbeidsvoorwaarden voor de geleverde uitzendkrachten (chauffeurs). De volgende arbeidsvoorwaarden zijn van toepassing:
B43: Salaris en Vergoedingen: De uitzendkracht ontvangt ten minste het wettelijke minimumloon of de caobepalingen die van toepassing zijn binnen de sector en voor de specifieke functie (zoals de cao voor het Bedrijfsgoederenvervoer).
B44: Werktijden en Rusttijden: De werktijden, pauzes en rusttijden worden overeenkomstig de geldende wetgeving en CAO Bedrijfsgoederenvervoer vastgesteld.
B45: Verlofregelingen: De uitzendkracht heeft recht op vakantiedagen, ziekteverlof en andere vergoedingen zoals voorgeschreven in de wet en CAO Bedrijfsgoederenvervoer.
B46: Pensioenregeling: De uitzendkracht wordt opgenomen in een pensioenregeling zoals bepaald door de wet en de CAO Bedrijfsgoederenvervoer.
B47: De Uitlener zal de uitzendkracht informeren over zijn rechten en verplichtingen volgens de geldende arbeidswetgeving en cao.
B49: 2. Algemeen
B51: 1. | C51: Inlener kan Uitlener verzoeken te bemiddelen in het ter beschikking stellen van chauffeurs aan Inlener, voor door Inlener te bepalen chauffeurswerkzaamheden en voor een door Inlener te bepalen periode.
B52: 2. | C52: Inlener is verplicht Uitlener te voorzien van alle informatie die Uitlener nodig heeft om de aangenomen opdracht goed te kunnen uitvoeren.
B53: 3. | C53: Met betrekking tot de uit te voeren werkzaamheden zal door partijen steeds een deelovereenkomst worden gesloten. In deze deelovereenkomst kan het volgende warden vastgelegd:
C54: ● | D54: Omschrijving van de uit te voeren werkzaamheden;
C55: ● | D55: Noodzakelijke kwalificaties en eventueel gewenste kwalificaties van het in te zetten personeel;
C56: ● | D56: Startdatum en verwachte einddatum;
C57: ● | D57: Het geschatte aantal uren dat de opdracht zal duren;
C58: ● | D58: Plaats van uitvoering;
C59: ● | D59: Prijsstelling en/of bijzonderheden.
B60: 4. | C60: Uitlener zal met de aan haar ter beschikking gestelde informatie op zoek gaan naar een geschikte (zelfstandige) chauffeur, om deze vervolgens met Inlener in contact te brengen. Inlener en de chauffeur maken vervolgens afspraken over de uit te voeren werkzaamheden, alsmede de daaraan verbonden voorwaarden en tarieven.
B62: 3. Opdracht
B64: 1. | C64: Inlener en Uitlener verklaren dat de overeenkomsten zijn/worden aangegaan als een overeenkomst van opdracht. Het bepaalde in de artikelen 7:400 e.v. Burgerlijk Wetboek is op deze overeenkomsten van toepassing, indien daarvan in deze overeenkomst niet is afgeweken.
B65: 2. | C65: Partijen verklaren uitdrukkelijk dat zij op geen enkel wijze hebben beoogd dat er een arbeidsovereenkomst in de zin van artikel 7:610 BW en aanverwante wetgeving wordt aangegaan. Uitlener fungeert louter als bemiddelaar tussen Inlener en een zelfstandige chauffeur die voor eigen rekening en risico chauffeurswerkzaamheden zal gaan verrichten.
B66: 3. | C66: Partijen verbinden zich als Inlener en Uitlener tegenover elkaar te gedragen.
B67: 4. | C67: Het is Uitlener niet toegestaan deze opdracht (gedeeltelijk) uit te besteden aan een of meer andere Inleners, behalve in het geval dat Inlener hiervoor vooraf uitdrukkelijke schriftelijke toestemming heeft verleend. Uitlener is verplicht te zorgen dat een uitbesteding steeds geschiedt onder dezelfde voorwaarden als tussen Inlener en Uitlener gelden.
B69: 4. Vergoeding
B71: 1. | C71: Voor de te verrichten werkzaamheden zal Inlener aan Uitlener een vergoeding verschuldigd zijn. Deze vergoeding bestaat uit de vergoeding die de zelfstandige chauffeur, na dit als zodanig te hebben afgesproken, aan de Inlener in rekening wenst te brengen te vermeerderen met een nader te bepalen additionele vergoeding voor de diensten van Uitlener.
B72: 2. | C72: Uitlener is verplicht om de vergoeding voor de opdracht aan Inlener te melden op het moment dat Uitlener de opdracht aan Inlener aanbiedt. Deze vergoeding zal in een overeenkomst/bevestigingsformulier warden vastgelegd.
B74: 5. Facturering
B76: 1. | C76: De vergoeding zal wekelijks door Uitlener aan Inlener met een gespecificeerde factuur in rekening worden gebracht.
B77: 2. | C77: Aan de door Uitlener ingediende factuur dient een bon te zijn gehecht die door Inlener voor akkoord is getekend en waaruit blijkt dat door de Inlener is geconstateerd dat de gefactureerde prestatie is geleverd. Op elke factuur dient het werk- en overeenkomst/opdrachtnummer te worden vermeld. Aan de factuur dienen ook bijbehorende urenregistratie toegevoegd te worden. In het urenregister moet in ieder geval worden vermeld: de volledige naam van de persoon, het aantal uren gewerkt, de dag en het tijdstip waarop de uren zijn gewerkt.
B78: 3. | C78: Indien de factuur voldoet aan de gestelde eisen en Uitlener heeft alle opgevraagde informatie en stukken verstrekt, zal betaling van de factuur door Inlener plaatsvinden binnen 14 dagen na factuurdatum.
B79: 4. | C79: De betalingen moeten geschieden in gangbare Nederlandse munt (Euro) op een door Uitlener aan te geven bankrekening.
B80: 5. | C80: Alle bedragen en prijzen genoemd in deze overeenkomst, zijn bedragen exclusief belastingen.
B82: 6. Instructierecht Inlener
B84: 1. | C84: Inlener is, in het kader van deze overeenkomst, gerechtigd de chauffeur rechtstreekse opdrachten en instructies te geven.
B86: 7. Identiteit
B88: 1. | C88: Uitlener verplicht zich van alle chauffeurs en ingeschakelde hulppersonen de identiteit op voorgeschreven wijze vast te stellen en een kopie van een geldig en origineel identiteitsbewijs te maken en te bewaren. Daarnaast dient Uitlener van de chauffeurs die niet de Nederlandse identiteit bezitten - een afschrift van een origineel verblijfsstatus en originele tewerkstellingsvergunning van deze personen te maken en te bewaren. Uitlener controleert de echtheid van het origineel identiteitsbewijs en of deze persoon gerechtigd is om in Nederland te werken.
B89: 2. | C89: Inlener is zelf ook verantwoordelijk voor het controleren van het origineel Identiteitsbewijs op echtheid en controleert zelf of het identiteitsbewijs, de originele verblijfsstatus en originele tewerkstellingsvergunning aan de betreffende persoon toebehoort.
B90: 3. | C90: Uitlener verplicht de chauffeurs om steeds bij de uitvoering van de werkzaamheden een origineel identiteitsbewijs mee te nemen naar Inlener, die Inlener op verzoek kan controleren.
B91: 4. | C91: Uitlener verstrekt voor aanvang van de werkzaamheden een afschrift van een geldig identiteitsbewijs van de personen die de werkzaamheden in het kader van deze overeenkomst van opdracht gaan verrichten en die niet uit de Europese Economische Ruimte (EER) komen.
B93: 8. Zelfstandigen zonder personeel (ZZP)
B95: 1. | C95: Inlener is er mee bekend dat de chauffeurs die hij via Uitlener ter beschikking krijgt gesteld zzp-ers zijn en geen dienstverband met Uitlener hebben.
B96: 2. | C96: Inlener vrijwaart Uitlener van iedere vorm van aansprakelijkheid jegens haar vanwege de inzet van deze chauffeurs.
B98: 9. Aangewezen instelling
B100: 1. | C100: Uitlener is verplicht te beschikken over een door KIWA Register afgegeven geldige aanwijzingsbeschikking voor het uitzenden van chauffeurs in het beroepsgoederenvervoer.
B101: 2. | C101: Ten bewijze daarvan dient Uitlener aan Inlener een kopie te verstrekken van de tussen Uitlener en chauffeur opgestelde (model) verklaring van terbeschikkingstelling.
B102: 3. | C102: Uitlener is verplicht om op eerste verzoek van Inlener te bewijzen dat zij beschikt over een door KIWA Register afgegeven geldige aanwijzingsbeschikking.
B103: 4. | C103: Indien en zodra Uitlener niet meer beschikt over een geldige aanwijzingsbeschikking of de certificering is opgeschort, is zij verplicht dit onmiddellijk te melden aan Inlener.
B105: 10. Duur en tussentijdse beëindiging
B107: 1. | C107: Deze raamovereenkomst gaat in op de datum van ondertekening en geldt voor onbepaalde tijd. Ook de lopende overeenkomsten worden per direct beheerst door de inhoud van deze raamovereenkomst. De raamovereenkomst kan te allen tijde schriftelijk worden opgezegd. Beide partijen zijn bevoegd de overeenkomst op te zeggen tegen het eind van elke maand met inachtneming van een opzegtermijn van 28 dagen, tenzij de redelijkheid en billijkheid zich hiertegen verzet. Enkel in gezamenlijk overleg kan een eerdere beëindigingsdatum overeengekomen worden. De raamovereenkomst blijft van toepassing op individuele overeenkomsten die voor het einde van deze raamovereenkomst zijn aangegaan.
B108: 2. | C108: Elke partij kan deze raamovereenkomst en/of een of meer individuele overeenkomsten direct (zonder dat rechterlijke tussenkomst en/of ingebrekestelling zijn vereist) (gedeeltelijk) beëindigen, zonder dat hij tot enige schadevergoeding is gehouden:
C109: ● | D109: Bij niet nakoming door de wederpartij van enige verplichting uit deze overeenkomst of een individuele overeenkomst, tenzij de wederpartij binnen zeven dagen alsnog de overeenkomst nakomt;
C110: ● | D110: Bij faillissement van de wederpartij, wanneer de wederpartij surseance van betaling aanvraagt of wanneer er beslag op haar goederen wordt gelegd;
C111: ● | D111: Indien de wederpartij toepassing van de wettelijke regeling van schuldsanering aanvraagt, de wederpartij onder curatele of (een gedeelte van) zijn vermogen onder bewind wordt gesteld of bij boedelafstand door de wederpartij;
C112: ● | D112: Bij handelingen in strijd met de wet- of regelgeving door een van de Partijen.
B113: 3. | C113: Uitlener is altijd bevoegd om de individuele overeenkomst(en) te beëindigen indien een chauffeur die de opdracht bij Inlener uitvoert niet (voldoende) functioneert of zich niet houdt aan de verstrekte opdracht.
B115: 11. Wijzigingen van en aanvullingen op de overeenkomst
B117: 1. | C117: Wijzigingen van en aanvullingen op deze overeenkomst zijn slechts geldig na schriftelijke vastlegging en ondertekening door partijen.
B118: 2. | C118: Indien een of meerdere bepalingen van deze overeenkomst nietig zijn (verklaard) of hun rechtsgeldigheid hebben verloren, zullen de overige bepalingen van deze overeenkomst van kracht blijven voor zover deze bepalingen niet zinledig zijn geworden.
B119: 3. | C119: Indien zich na ondertekening van de overeenkomst wijzigingen voordoen in wetgeving of regelgeving van dwingendrechtelijke aard en indien een en ander consequenties heeft voor de inhoud en/of uitvoering van de overeenkomst, zullen partijen andere afspraken met elkaar maken en daarbij zo dicht mogelijk bij de inhoud van de oorspronkelijke bedoelingen van partijen blijven.
B121: 12. Aansprakelijkheid
B123: 1. | C123: De aansprakelijkheid van de Partijen is beperkt tot het door zijn aansprakelijkheidsverzekering uitgekeerde bedrag, verhoogd met het eigen risico. Ingeval er geen uitkering plaatsvindt is de aansprakelijkheid tot schadevergoeding beperkt tot een bedrag van €1.500 (duizend vijfhonderd euro).
B124: 2. | C124: Uitlener is verplicht de nodige verzekeringen af te sluiten die zijn aansprakelijkheidsrisico's voldoende dekken.
B125: 3. | C125: Uitlener kan niet aansprakelijk worden gehouden voor indirecte schade, waaronder gederfde winst, gevolgschade en schade door bedrijfsstagnatie.
B126: 4. | C126: Uitlener kan niet aansprakelijk worden gehouden door derden met betrekking tot rechten van intellectuele eigendom op door Inlener verstrekte zaken ten behoeve van de uitvoering van de opdracht.
B127: 5. | C127: Inlener is aansprakelijk ingeval Uitlener schade leidt door een gevaar bij het uitoefenen van de opdracht, mits dit gevaar niet behoort tot de normale risico's van de bedrijfsuitoefening van de onderneming van Uitlener en het gevaar niet is meegewogen in de hoogte van de vergoeding.
B128: 6. | C128: Partijen zijn niet aansprakelijk voor een tekortkoming door een omstandigheid die niet te voorzien was en niet te wijten valt aan de schuld van beide of een der Partijen in de zin van art. 6:75 BW. Partijen stellen elkaar schriftelijk op de hoogte indien een dergelijke situatie, waarin nakoming van de overeenkomst in het gedrang komt, zich voordoet.
B130: 13. Wanprestatie, vernietiging en nietigheid
B132: 1. | C132: Indien er sprake is van wanprestatie in de zin van art. 6:74 BW en nakoming van de overeenkomst niet blijvend onmogelijk is geworden, ontstaat voor Partijen de mogelijkheid de wederpartij in gebreke te stellen ten behoeve van een juiste uitvoering van de overeenkomst.
B133: 2. | C133: Macht de ingebrekestelling per aangetekende post of e-mail met ontvangstbevestiging binnen redelijke termijn zonder gevolg blijven, dan behoudt de Partij die niet in gebreke is gesteld het recht de overeenkomst te beëindigen.
B134: 3. | C134: Ingeval een bepaling in deze overeenkomst wordt vernietigd of nietig wordt verklaard, dan geldt deze vernietiging of nietigheid enkel voor de betreffende bepaling. Andere bepalingen in deze overeenkomst blijven onverlet.
B136: 14. Meewerken aan Loonvalidatie door de Inlener
B138: De Uitlener zal volledige medewerking verlenen aan een loonvalidatie die wordt uitgevoerd door een inspectieinstelling, aangewezen door de Inlener. De loonvalidatie is bedoeld om te waarborgen dat de afgesproken lonen en arbeidsvoorwaarden correct worden nageleefd.
...

Sheet AgrPlan
B1: Arbeidsovereenkomst bepaalde tijd – Planner Vervoer over de Weg
B3: De ondergetekenden:
B5: 1. De uitzendonderneming DeNeX Uitzendbureau B.V. gevestigd te Barendrecht aan de Gebroken Meeldijk 66, Unit 1.15 , 2991 VD, vertegenwoordigd door dhr. D.O. Ibryam , hierna te noemen: werkgever;
B7: 2. mw. S.E. Fidanova, geboren op 09 juli 1986, wonende te Florastraat 49, 2672 HL NAALDWIJK, hierna te noemen: werknemer;
B9: verklaren het volgende te zijn overeengekomen:
B11: Artikel 1 – Duur van de overeenkomst
B13: Deze arbeidsovereenkomst wordt aangegaan voor bepaalde tijd, te weten 7 maanden, ingaande op 04 juni 2025 en eindigende van rechtswege op 03 januari 2026, zonder dat opzegging vereist is.
B15: Artikel 2 – Proeftijd
B16: Dit arbeidscontract is aangegaan met inachtneming van een wederzijdse proeftijd van 1 maand. Gedurende deze proeftijd kunnen beide partijen het arbeidscontract met directe ingang beëindigen. Een schriftelijke bevestiging hiervan is niet benodigd. De proeftijd is van toepassing indien een dienstverband voor een minimale duur van 12 maanden is aangegaan.
B18: Artikel 3 – Functie en werkzaamheden
B20: Werknemer treedt in dienst in de functie van Planner Vervoer over de Weg. Hij/Zij verricht alle werkzaamheden die in redelijkheid van hem/haar in deze functie mogen worden verwacht, alsmede alle andere werkzaamheden die door werkgever worden opgedragen en die verband houden met de onderneming.
B22: Artikel 4 – Arbeidsduur en werktijden
... B67: Artikel 10 – Toepasselijk recht en geschillen
B69: ="Op deze overeenkomst is Nederlands recht van toepassing. Geschillen zullen bij uitsluiting worden voorgelegd aan de bevoegde rechter te "&FillIn!H8&"." -> Op deze overeenkomst is Nederlands recht van toepassing. Geschillen zullen bij uitsluiting worden voorgelegd aan de bevoegde rechter te Barendrecht.
B71: ="Aldus overeengekomen en in tweevoud getekend te "&FillIn!H8&" op "&TEXT(FillIn!D52,"dd mmmm yyyy")&"." -> Aldus overeengekomen en in tweevoud getekend te Barendrecht op 17 november 2025.
B73: Werkgever | G73: Werknemer
B74: ="Naam: "&FillIn!M5 -> Naam: de heer D.O. Ibryam | G74: ="Naam: "&FillIn!M4 -> Naam: de heer G. Aslan
B79: Handtekening: ...................................... | G79: Handtekening: ......................................

Sheet AODriver
B1: ="ARBEIDSOEVEENKOMST VOOR "&IF(FillIn!D12>0,"BEPAALDE","ONBEPAALDE")&" TIJD" -> ARBEIDSOEVEENKOMST VOOR BEPAALDE TIJD
B3: De ondergetekenden:
B4: Werkgever: | G4: Werknemer:
B5: Bedrijfsnaam | C5: : | D5: =FillIn!H4 -> DeNeX Uitzendbureau B.V. | G5: Naam | H5: : | I5: =FillIn!M4 -> de heer G. Aslan
B6: Adres | C6: : | D6: =FillIn!H6 -> Gebroken Meeldijk 66, Unit 1.15 | G6: Adres | H6: : | I6: =FillIn!D5 -> Bikscotelaan 248 /2/2140 Borgerhout
B7: Postcode/Plaats | C7: : | D7: =FillIn!H7&" "&FillIn!H8 -> 2991 VD Barendrecht | G7: Postcode /Plaats | H7: : | I7: =FillIn!D6&" "&FillIn!D7 -> 2140 An twerp
B8: Contact | C8: : | D8: =FillIn!M5 -> de heer D.O. Ibryam | G8: Geb.datum | H8: : | I8: =FillIn!D8 -> 29310
G9: BSN: | H9: : | I9: =FillIn!D9 -> 235116026
B10: zijn het volgende overeengekomen:
B12: Artikel 1: Datum indiensttreding, functie en plaats werkzaamheden
B13: ="Er is een dienstverband aangegaan met ingang van: "&TEXT(FillIn!D11,"dd mmmm yyyy")&IF(FillIn!D12>0," tot "&TEXT(FillIn!D12,"dd mmmm yyyy")&".",".") -> Er is een dienstverband aangegaan met ingang van: 18 november 2025 tot 17 mei 2026.
B15: ="De werknemer is aangenomen voor de functie van "&FillIn!D13&"." -> De werknemer is aangenomen voor de functie van Chauffeur.
B17: De bij deze functie behorende werkzaamheden bestaan uit: Het vervoeren van goederen over weg en voorts alle werkzaam­heden die redelijkerwijs van hem verlangd kunnen worden. De werkzaamheden worden uitgevoerd vanuit de vestiging van werkgever of opdrachtgevers van werkgever.
B19: Artikel 2: Proeftijd
B20: =IF(FillIn!D14>0,"Dit arbeidscontract is aangegaan met inachtneming van een wederzijdse proeftijd van "&FillIn!D14&". Gedurende deze proeftijd kunnen beide partijen het arbeidscontract met directe ingang beëindigen. Een schriftelijke bevestiging hiervan is niet benodigd. De proeftijd is van toepassing indien een dienstverband voor een minimale duur van 12 maanden is aa"&"ngegaan.","Er is geen proeftijd bij het aangaan van de dienstverband.") -> Er is geen proeftijd bij het aangaan van de dienstverband.
B22: Artikel 3: Arbeidsduur, werktijden en overwerk
B23: ="De wekelijkse arbeidsduur bedraagt "&FillIn!D15&"." -> De wekelijkse arbeidsduur bedraagt 40 uur per week.
B24: ="Werknemer verklaart op de hoogte te zijn van en in te stemmen met de door werkgever geregelde wekelijkse planning voor "&FillIn!D16&". Werknemer is tevens op de hoogte gesteld dat de werktijden tussen "&FillIn!D17&" kunnen plaatsvinden. Werknemer is redelijkerwijs verplicht gehoor te geven aan een redelijk verzoek van ­werkgever om overwerk te verrichten." -> Werknemer verklaart op de hoogte te zijn van en in te stemmen met de door werkgever geregelde wekelijkse planning voor maandag t/m vrijdag. Werknemer is tevens op de hoogte gesteld dat de werktijden tussen tussen 7:00 uur t/m 19:00 uur kunnen plaatsvinden. Werknemer is redelijkerwijs verplicht gehoor te geven aan een redelijk verzoek van ­werkgever om overwerk te verrichten.
B26: Artikel 4: Salaris
B27: ="Werknemer ontvangt conform de cao en loonschaal "&FillIn!D21&" en trede "&FillIn!D22&" een salaris van € "&FillIn!D24&" bruto per uur door werkgever te voldoen voor of op de laatste dag van de maand." -> Werknemer ontvangt conform de cao en loonschaal D en trede 5 een salaris van € 18,71 bruto per uur door werkgever te voldoen voor of op de laatste dag van de maand.
B29: Artikel 5: Reiskostenvergoeding
B30: ="De werknemer ontvangt geen vergoeding voor de reiskosten woon-werkverkeer. Indien achteraf hierover schriftelijk wordt overeengekomen bedraagt de vergoeding maximaal € "&FillIn!D25&" per gereisde kilometer met een maximum reiskostenvergoeding van € "&FillIn!D26&" per maand. De reiskostenvergoeding is onbelast en maakt geen deel uit van het loon van de werknemer." -> De werknemer ontvangt geen vergoeding voor de reiskosten woon-werkverkeer. Indien achteraf hierover schriftelijk wordt overeengekomen bedraagt de vergoeding maximaal € 0,23 per gereisde kilometer met een maximum reiskostenvergoeding van € 100 per maand. De reiskostenvergoeding is onbelast en maakt geen deel uit van het loon van de werknemer.
B32: Artikel 6: Salaris bij arbeidsongeschiktheid en wachtdagen
B33: 1. In geval van arbeidsongeschiktheid wegens ziekte, ongeval en dergelijke, zal werkgever, indien en zolang in die periode het dienstverband voortduurt, gedurende de eerste 104 weken van arbeidsongeschiktheid 70% van het brutoloon door­betalen, doch gedurende de eerste 52 weken ten minste het voor werknemer geldende ­minimumloon.
B34: 2. Werknemer verklaart op de hoogte te zijn van en in te stemmen met de door werkgever vastgestelde voorschriften in verband met ziekmelding en controle.
B35: 3. Wegens ziekte of arbeidsongeschiktheid heeft de werknemer gedurende de eerste dag van een ziekteperiode geen recht op loon. Dit geldt niet indien werknemer na het einde van een ziekteperiode binnen vier weken wederom ziek wordt.
B37: Artikel 7: Re-integratie na einde dienstverband
B38: - Werknemer is verplicht zich onmiddellijk ziek te melden bij werkgever conform de door werkgever vastgestelde voorschriften in verband met ziekmelding en controle als werknemer binnen 4 weken na het einde van de arbeidsovereenkomst ziek wordt en op dat moment niet werkzaam is bij een andere werkgever of een WW-uitkering ontvangt.
B39: - Als werknemer ziek is op het moment dat hij uit dienst gaat en/of als werknemer voldoet aan het bepaalde in lid 1 van dit artikel, dient werknemer zich te blijven houden aan de door werkgever of regelgeving vastgestelde voorschriften in verband met ziekmelding en controle.
B40: - Indien werknemer bovenstaande van de in dit artikel bepaalde overtreedt, verbeurt hij aan werkgever een direct opeisbare boete van 2.500,- voor iedere overtreding, alsmede een bedrag van 500,- voor iedere dag dat de overtreding voortduurt. De boete zal verschuldigd zijn door het enkele feit van de overtreding of niet-nakoming, maar laat onverminderd het recht om volledige schadevergoeding te vorderen. Deze boete is rechtsreeks verschuldigd aan werkgever en strekt deze tot voordeel. Hiermee wordt nadrukkelijk afgeweken van het bepaalde in artikel 7:650 leden 3 en 5 BW.
B42: Artikel 8: Vakantiedagen, ATV en vakantiebijslag
B43: ="Werknemers van "&FillIn!D32&" hebben recht op "&FillIn!D33&" vakantiedagen per kalenderjaar ("&VALUE(LEFT(FillIn!D33,2))-4&" wettelijke en 4 dagen bovenwettelijke) met behoud van salaris." -> Werknemers van 45 t/m 49 jaar hebben recht op 25 dagen vakantiedagen per kalenderjaar (21 wettelijke en 4 dagen bovenwettelijke) met behoud van salaris.
B44: Bij andere leeftijden gelden andere rechten, zie hiervoor artilkel 67a van het cao. Van de vakantiedagen mogen maximaal drie weken worden opgenomen in een aaneengesloten periode. ")Verlofdagen worden vastgesteld door de werkgever, na overleg met de werknemerVerlofdagen worden vastgesteld door de werkgever, na overleg met de werknemer. Werkgever is bevoegd maximaal 14 dagen per jaar als verplichte vakantiedagen aan te wijzen. Tevens is het mogelijk dat een periode (maximaal één maand) wordt aangewezen i.v.m. bedrijfssluiting. Deze wordt door werkgever als verplichte vakantie aangewezen. Deze vakantiedagen komen in mindering op het vakantietegoed.
B45: ="Werknemer heeft recht op "&FillIn!D34&" ATV dagen per kalenderjaar met behoud van salaris. Per jaar heeft de werknemer recht op een vakantiebijslag van "&TEXT(FillIn!D35,"0.00%")&" over het op jaarbasis berekende brutosalaris." -> Werknemer heeft recht op 3,5 ATV dagen per kalenderjaar met behoud van salaris. Per jaar heeft de werknemer recht op een vakantiebijslag van 8,00% over het op jaarbasis berekende brutosalaris.
B46: ="Werknemer ontvangt in de maanden mei en november de vakantiebijslag van "&TEXT(FillIn!D35,"0.00%")&" naar ratio tezamen met de maandelijkse salaris. Bij tussentijdse aanvang of beëindiging van het dienstverband worden de vakantie­rechten naar rato van het aantal maanden dat werknemer in dienst is, vastgesteld." -> Werknemer ontvangt in de maanden mei en november de vakantiebijslag van 8,00% naar ratio tezamen met de maandelijkse salaris. Bij tussentijdse aanvang of beëindiging van het dienstverband worden de vakantie­rechten naar rato van het aantal maanden dat werknemer in dienst is, vastgesteld.
B48: Artikel 9: Arbeids- en bedrijfsregels
B49: Werknemer verklaart op de hoogte te zijn van en in te stemmen met de bij werkgever geldende arbeids- en bedrijfsregels en een exemplaar van deze arbeids- en bedrijfsregels te hebben ontvangen.
B51: Artikel 10: Schadeclausule bij niet nakomen van verplichtingen
B52: Indien werknemer om wat voor reden dan ook de arbeidsovereenkomst c.q. de werkzaamheden eenzijdig beëindigt zonder hier werkgever van tevoren van op de hoogte te stellen of zich niet houdt aan de geldende opzegtermijn is werknemer schadeplichtig. In afwijking van art. 7:650 leden 3 en 5 BW zal werknemer in dat geval een onmiddellijk opeisbare tot voordeel van de werkgever strekkende boete verbeuren van € 250,00 ineens (welke direct al wordt ingehouden op het salaris van werknemer) onverminderd het recht van werkgever om in plaats van deze boete, schadevergoeding te vorderen. Eveneens staat de werknemer de inhouding van de schadevergoeding op het loon toe rekening houdend met WML.
B54: Artikel 11: Wijzigingen
B55: Werkgever behoudt zicht het recht voor om éénzijdig de arbeidsvoorwaarden te ­wijzigen, met inachtneming van hetgeen bepaald is in artikel 7:613 van het Burgerlijk Wetboek. Dit indien hij daarbij een zodanig zwaarwichtig belang heeft dat het belang van de werknemer dat door de wijziging wordt geschaad, daardoor naar maatstaven van redelijkheid en billijkheid moet wijken. Bij wijziging van fiscale regelgeving en/of fiscale besluiten waardoor een in deze overeenkomst genoemde fiscale faciliteit wordt gewijzigd, beperkt dan wel komt te vervallen zal de desbetreffende bepaling in deze overeenkomst overeenkomstig worden aangepast.
B57: Artikel 12: Geheimhoudingsbeding
B58: Werknemer zal zowel gedurende als na afloop van deze arbeidsovereenkomst strikte geheimhouding betrachten omtrent al hetgeen bij de uitoefening van zijn/haar functie te zijner kennis komt in verband met zaken en belangen van de onderneming van werkgever of een met haar gelieerde onderneming. Deze plicht tot geheimhouding omvat eveneens alle gegevens c.q. bijzonderheden van relaties en cliënten van werkgever, waarvan werknemer uit hoofde van zijn/haar functie kennisneemt.
B60: Artikel 13: Teruggavebeding
B61: Alle stukken en andere schriftelijke informatie en alle hard- en software die werknemer in het kader van zijn werkzaamheden heeft gebruikt en eigendom zijn van werkgever of welke werknemer in het kader van zijn werkzaamheden heeft vervaardigd, blijven/worden eigendom van werkgever. Werknemer dient deze bescheiden aan werkgever te retourneren indien werkgever daarom vraagt en/of indien deze arbeidsovereenkomst eindigt, zonder dat werknemer hiervan op enigerlei wijze een kopie mag behouden en/of aan derden mag verstrekken. Bij beëindiging van deze arbeidsovereenkomst is werknemer verplicht om alle door werkgever ter beschikking gestelde bedrijfseigendommen onmiddellijk aan werkgever terug te geven.
B63: Artikel 14: Gedragscode voor internet-, e-mail- en social media-gebruik
B64: Werkgever hanteert een gedragscode voor internet-, e-mail- en social media-gebruik waarin voorschriften zijn opgenomen ten aanzien van het internet- en e-mailgebruik en (zakelijk) gebruik van social media. Werknemer heeft een exemplaar van de gedragscode voor internet-, e-mail- en social media-gebruik ontvangen en verklaart zich door ondertekening van deze arbeidsovereenkomst akkoord met de inhoud van deze gedragscode.
... B67: Nederlands recht is van toepassing op deze arbeidsovereenkomst, alsmede op alle geschillen die samenhangen met of voortvloeien uit deze arbeidsovereenkomst. De van toepassing zijnde cao is Beroepsgoederenvervoer.
B69: ="Werknemer verklaart een getekend exemplaar van dit contract en een geparafeerde exemplaar de arbeids- en bedrijfsregels te hebben ont­vangen. " -> Werknemer verklaart een getekend exemplaar van dit contract en een geparafeerde exemplaar de arbeids- en bedrijfsregels te hebben ont­vangen.
B71: ="Aldus overeengekomen en in tweevoud getekend te "&FillIn!H8&" op "&TEXT(FillIn!D52,"dd mmmm yyyy")&"." -> Aldus overeengekomen en in tweevoud getekend te Barendrecht op 17 november 2025.
B73: ="Werkgever: "&FillIn!H4 -> Werkgever: DeNeX Uitzendbureau B.V. | F73: ="Werknemer: "&FillIn!M4 -> Werknemer: de heer G. Aslan
B74: ="Namens deze: "&FillIn!M5 -> Namens deze: de heer D.O. Ibryam
B80: Handtekening | F80: Handtekening

Sheet TempAO
B1: UITZENDOVEREENKOMST FASE A
B3: De ondergetekenden:
B4: Partijen:
B5: 1. | C5: ="De uitzendonderneming "&FillIn!H4&" gevestigd te Rijswijk aan de "&FillIn!H6&", "&FillIn!H7&", te "&FillIn!H8&" vertegenwoordigd door "&FillIn!M5&"." -> De uitzendonderneming DeNeX Uitzendbureau B.V. gevestigd te Rijswijk aan de Gebroken Meeldijk 66, Unit 1.15, 2991 VD, te Barendrecht vertegenwoordigd door de heer D.O. Ibryam.
C7: hierna te noemen : | F7: Werkgever
C9: en
B11: 2. | C11: De medewerker: | F11: =FillIn!M4 -> de heer G. Aslan
C12: Adres: | F12: =FillIn!D5 -> Bikscotelaan 248 /2/2140 Borgerhout
C13: Plaats: | F13: =FillIn!D6&" "&FillIn!D7 -> 2140 An twerp
C14: Geboortedatum: | F14: =FillIn!D8 -> 29310
C15: BSN: | F15: =FillIn!D9 -> 235116026
C17: Partij nader te noemen | F17: Werknemer
B19: ZIJN MET ELKAAR OVEREENGEKOMEN:
B21: Artikel 1: | D21: Functie
B22: 1.1. | C22: ="Per "&TEXT(FillIn!D11,"dd mmmm yyyy")&" treedt "&FillIn!M4&" indienst bij "&FillIn!H4&" voor de duur van de projecten welke "&FillIn!H4&" heeft afgesloten met verschillende opdrachtgevers." -> Per 18 november 2025 treedt de heer G. Aslan indienst bij DeNeX Uitzendbureau B.V. voor de duur van de projecten welke DeNeX Uitzendbureau B.V. heeft afgesloten met verschillende opdrachtgevers.
B23: 1.2. | C23: =FillIn!M4&" zal als "&FillIn!D13&" worden ingezet voor de arbeidsduur van "&FillIn!D15&"." -> de heer G. Aslan zal als Chauffeur worden ingezet voor de arbeidsduur van 40 uur per week.
C24: ="Naar verwachting zal de arbeidsovereenkomst doorlopen tot "&TEXT(FillIn!H41,"dd mmmm yyyy")&". " -> Naar verwachting zal de arbeidsovereenkomst doorlopen tot 17 juni 2026.
C25: =FillIn!M4&" werkt onder toezicht van de opdrachtgever voor wie werknemer de werkzaamheden gaat verrichten." -> de heer G. Aslan werkt onder toezicht van de opdrachtgever voor wie werknemer de werkzaamheden gaat verrichten.
B26: 1.3. | C26: Proeftijd conform artikel 16 CAO ABU, dhr. N.V. Stoev kan de CAO ABU nalezen op www.ABU.nl.
B28: Artikel 2: | D28: CAO ABU
B29: Op deze arbeidsovereenkomst is tevens de Collectieve Arbeidsovereenkomst voor Uitzendkrachten (CAO ABU,
B30: https://www.abu.nl/app/uploads/2024/12/ABU-CAO-Uitzendkrachten-2024.pdf) van toepassing.
B32: Artikel 3: | D32: Uitzendbeding
B33: 3.1. | C33: Op deze uitzendovereenkomst is de bepaling ex artikel 7:691 lid 2 BW in combinatie met de artikelen 12 en 13 van de CAO ABU van toepassing. Dat betekent dat de uitzendovereenkomst van rechtswege eindigt doordat de terbeschikkingstelling van de uitzendkracht door de uitzendonderneming aan de opdrachtgever op verzoek van de opdrachtgever ten einde komt.
B34: 3.2 | C34: Indien fase A van toepassing is, wordt de arbeidsovereenkomst als beëindigd beschouwd ingeval van ziekte of ongeval. Als moment voor de beëindiging geldt alsdan de datum van ziekmelding bij de opdrachtgever en/of de werkgever.
B36: Artikel 4: | D36: Loon, inhouding en vergoedingen
B37: ="Het bruto uurloon bedraagt: € "&FillIn!D24&" en zal door "&FillIn!H4&" worden voldaan op basis van een 40 urige werkweek." -> Het bruto uurloon bedraagt: € 18,71 en zal door DeNeX Uitzendbureau B.V. worden voldaan op basis van een 40 urige werkweek.
B38: Bij beëindiging van de arbeidsovereenkomst wordt gedurende zes weken een bedrag van € 500,- van het uit te betalen salaris ingehouden als voorzorgsmaatregel tegen eventuele boetes of sancties die aan de werkgever te laat zijn bereikent.
B40: Overige afspraken
B41: ▪ | C41: Werknemer heeft recht op 10,92% vakantiedagentoeslag
B42: ▪ | C42: 8,33% vakantietoeslag over de gewerkte uren;
B43: ▪ | C43: Opzegtermijn volgens CAO ABU;
B44: ▪ | C44: Opbouw feestdagen volgens CAO ABU;
B45: ▪ | C45: Pensioen volgens CAO ABU;
B46: ▪ | C46: Kort verzuim volgens CAO ABU;
B47: ▪ | C47: Werkgever betaalt volledig de wettelijke bijdrage ziektekosten (bijtelling werknemer);
B48: ▪ | C48: Werkgever houdt de overuren bij en betaalt uit tijdens vakantie tegen gewerkte uurtarief.
B50: Artikel 5: | D50: clausule ‘Vangnetter’
B51: 5.1. | C51: De werknemer die binnen 4 weken na het einde van het dienstverband ziek wordt, en op dat moment niet werkzaam is bij een andere werkgever of een WW-uitkering geniet, meldt zich onmiddellijk ziek bij werkgever conform de bij werkgever geldende regels omtrent ziekmeldingen;
B52: 5.2. | C52: De werknemer die ziek is op het moment dat hij uit dienst gaat en de werknemer die voldoet aan het bepaalde in lid 1 van dit artikel, dient:
B53: ▪ | C53: gehoor te geven aan een oproep van de bedrijfsarts en/of arbeidsdeskundige van werkgever;
B54: ▪ | C54: aan werkgever alle informatie te verstrekken die hij op grond van de Ziektewet of de WIA aan werkgever als eigenrisicodrager of aan het UWV dient te verstrekken. Indien de werknemer geen toestemming geeft medische gegevens aan werkgever te verstrekken dient hij deze wel aan een bedrijfsarts of arts-gemachtigde te verstrekken;
B55: ▪ | C55: alle verplichtingen na te komen die volgen uit de Ziektewet en de WIA;
B56: ▪ | C56: mee te werken aan en namens werkgever aangeboden re-integratietraject of proefplaatsing;
B57: ▪ | C57: een (vervroegde) IVA-uitkering aan te vragen indien en zodra de bedrijfsarts dit mogelijk acht.
B58: 5.3. | C58: De verplichtingen hierboven genoemd in lid 2 van dit artikel blijven bestaan zolang de werknemer arbeidsongeschikt blijft en een Ziektewetuitkering geniet. Is de werknemer volledig hersteld dan eindigen de verplichtingen, tenzij de werknemer binnen 4 weken na hersteld melding opnieuw arbeidsongeschikt raakt.
B59: 5.4. | C59: Indien de werknemer het in lid 1 lid 2 van dit artikel bepaalde overtreedt, verbeurt hij aan de werkgever een direct opeisbare boete van € 2.500,- voor iedere overtreding, alsmede een bedrag van € 500,- voor iedere dag, dat de overtreding voortduurt. De boete zal verschuldigd zijn door het enkele feit van overtreding of niet-nakoming, maar laat onverminderd het recht van de werkgever nakoming te vorderen en onverminderd het recht om volledige schadevergoeding te vorderen. Deze boete is rechtstreeks verschuldigd aan de werkgever en strekt deze tot voordeel. Hiermee wordt nadrukkelijk afgeweken van het bepaalde in artikel 7:650 leden 3 en 5 BW.
B61: Wij adviseren je i.v.m. wetswijzigingen actie te ondernemen een week voordat jouw tijdelijke contract afloopt. Vraag een week voor einde contract een WW uitkering aan, wij willen jou daar graag bij helpen.
B63: Artikel 6: | D63: Voorwaarden
B64: Werknemer aanvaardt deze dienstbetrekking op de hierboven en hierna omschreven voorwaarden en verbindt zich de hem door werkgever opgedragen werkzaamheden naar beste vermogen te verrichten.
B66: Van de werknemer wordt een creatieve inzet verwacht, waarbij ook niet in de taakomschrijving opgenomen werkzaamheden zullen worden verricht die zullen leiden tot het bereiken van de ondernemingsdoelen.
B68: Geheimhoudingsbeding
B69: Zowel gedurende als na het einde van de dienstbetrekking zal werknemer volstrekte geheimhouding betrachten ten aanzien van alle gegevens welke hem omtrent werkgever en de activiteiten van werkgever en met werkgever gelieerde ondernemingen bekend zijn. Deze geheimhoudingsplicht omvat tevens alle gegevens van klanten of andere relaties van werkgever, waarvan werknemer uit hoofde van zijn functie kennis neemt. Voor iedere overtreding van deze bepaling verbeurt de werknemer aan de werkgever een terstond opeisbare boete van € 10.000,00 onverminderd het recht van werkgever op volledige schadevergoeding.
B70: Overtreding van het hiervoor vermelde verbod kan voor werkgever een dringende reden vormen voor ontslag op staande voet, en zal aanleiding kunnen geven om bij de Officier van Justitie aangifte te doen van het plegen van een misdrijf als bedoeld in artikel 273 Wetboek van Strafrecht.
B72: Nevenarbeid
B73: Tijdens het dienstverband zal de werknemer zonder schriftelijke toestemming van de werkgever geen al dan niet gehonoreerde beroepsmatige nevenfuncties bekleden.
B74: Tevens is het de werknemer verboden om van afnemers, leveranciers of derden gedurende de duur van de arbeidsovereenkomst zonder voorafgaande schriftelijke toestemming van de werkgever, direct of op enigerlei wijze indirect provisie, tegemoetkoming of vergoeding, in welke vorm dan ook aan te nemen of te bedingen.
B76: Artikel 7: | D76: Gebruik eigendommen van de werkgever
B77: De werknemer zal de eigendommen van de werkgever met zorg behandelen.
B79: De eigendommen van de werkgever die de werknemer in bruikleen heeft, blijven altijd eigendom van de werkgever en moeten op verzoek van de werkgever onmiddellijk in de oorspronkelijke staat geretourneerd worden.
B81: Artikel 8: | D81: Slotbepalingen
B82: De werknemer zal voorafgaand aan de datum van indiensttreding aan de werkgever een geldig identiteitsbewijs als bedoeld in de Wet op identificatieplicht (Stb. 1993, 660) verstrekken, zodat de werkgever de identiteit van de werknemer kan verifiëren. Werkgever voornoemd identiteitsbewijs, digitaal en/of hard copy - conform haar wettelijke verplichting opnemen in het personeelsdossier.
B83: De werknemer verplicht zich er toe, zoals bepaald in de Wet op de identificatieplicht, om tijdens de arbeidsuren een geldig identiteitsbewijs, dan wel een geldig rijbewijs, bij zich te hebben.
B84: Door ondertekening van deze arbeidsovereenkomst verklaren werknemer en werkgever zich akkoord met het hierin gestelde.
B85: ="Aldus overeengekomen en in tweevoud getekend te "&FillIn!H8&" op "&TEXT(FillIn!D52,"dd mmmm yyyy")&"." -> Aldus overeengekomen en in tweevoud getekend te Barendrecht op 17 november 2025.
B87: =FillIn!H4 -> DeNeX Uitzendbureau B.V. | H87: Werknemer
B92: =FillIn!M5 -> de heer D.O. Ibryam | H92: =FillIn!M4 -> de heer G. Aslan

Sheet KIWA
B2: VERKLARING VAN TERBESCHIKKINGSTELLING
B3: Wet wegvervoer goederen
B4: 2 | C4: 0 | D4: 2 | E4: 2 | F4: - | G4: 2 | H4: 8 | I4: 3 | J4: 4
F5: Nummer:
B7: Aangewezen instelling: | L7: =FillIn!H4 -> DeNeX Uitzendbureau B.V.
B8: Adres: | L8: =FillIn!H6 -> Gebroken Meeldijk 66, Unit 1.15
L9: =FillIn!H7&" "&FillIn!H8 -> 2991 VD Barendrecht
B10: Telefoon: | L10: =FillIn!H9 -> +31628813127
B12: Verklaart ter beschikking te hebben gesteld aan:
B13: ="Naam vergunninghouder: "&FillIn!H4 -> Naam vergunninghouder: DeNeX Uitzendbureau B.V.
B14: 3 | C14: 2 | D14: 5 | E14: 3 | F14: 0 | G14: . | H14: . | I14: . | J14: . | K14: .
E16: Codenummer NIWO:
C17: De chauffeur:
B18: Naam en voorletters: | L18: =FillIn!O4 -> Aslan, G.
B19: Geboren op: | L19: =FillIn!D8 -> 29310
B20: Wonende te: | L20: =FillIn!D5 -> Bikscotelaan 248 /2/2140 Borgerhout
B21: Volledig adres: | L21: =FillIn!D6&" "&FillIn!D7 -> 2140 An twerp
C23: en verklaart de op dit formulier vermelde gegevens naar waarheid te hebben verstrekt en een kopie
C24: van deze verklaring aan de hierboven vermelde bestuurder van een vrachtauto te hebben uitgereikt.
B26: Datum uitreiking chauffeur | L26: =VLOOKUP(FillIn!$D$4,Employee!$A$3:$T$37,10,false) -> 45979
B28: Datum aanvang terbeschikkingstelling: | L28: =L26 -> 45979
B30: Datum einde terbeschikkingstelling: | L30: =L26+211 -> 46190
B32: Plaats: Barendrecht
B35: Handtekening aangewezen instelling: | O35: Handtekening chauffeur:
B40: =FillIn!M5 -> de heer D.O. Ibryam | O40: =FillIn!M4 -> de heer G. Aslan
B54: N.B. De bestuurder van een motorrijtuig is verplicht bij beëindiging van de terbeschikkingstelling deze verklaring in te leveren bij degene die hem ter beschikking heeft gesteld.

Sheet Schalen25
A1: TLN - Functieloonschalen per 1 januari 2025(+4%)
A2: Loonschaal/ trede | D2: Bedragen per: | G2: Uurloon à:
D3: Week | E3: 4 weken | F3: Maand | G3: 1 | H3: 1.3 | I3: 1.5
A4: A 1 | B4: A | C4: 1 | D4: 562.4 | E4: 2249.6 | F4: 2446.44 | G4: 14.06 | H4: 18.28 | I4: 21.09
A5: A 2 | B5: A | C5: 2 | D5: 569.12 | E5: 2276.48 | F5: 2474.53 | G5: 14.23 | H5: 18.5 | I5: 21.35
A6: A 3 | B6: A | C6: 3 | D6: 591.88 | E6: 2367.52 | F6: 2573.49 | G6: 14.8 | H6: 19.24 | I6: 22.2
A7: A 4 | B7: A | C7: 4 | D7: 615.55 | E7: 2462.2 | F7: 2676.41 | G7: 15.39 | H7: 20.01 | I7: 23.09
A8: A 5 | B8: A | C8: 5 | D8: 640.17 | E8: 2560.68 | F8: 2783.46 | G8: 16 | H8: 20.8 | I8: 24
A9: A 6 | B9: A | C9: 6 | D9: 665.78 | E9: 2663.12 | F9: 2894.81 | G9: 16.64 | H9: 21.63 | I9: 24.96
A10: B 1 | B10: B | C10: 1 | D10: 576.08 | E10: 2304.32 | F10: 2504.8 | G10: 14.4 | H10: 18.72 | I10: 21.6
A11: B 2 | B11: B | C11: 2 | D11: 599.12 | E11: 2396.48 | F11: 2604.97 | G11: 14.98 | H11: 19.47 | I11: 22.47
A12: B 3 | B12: B | C12: 3 | D12: 623.08 | E12: 2492.32 | F12: 2709.15 | G12: 15.58 | H12: 20.25 | I12: 23.37
A13: B 4 | B13: B | C13: 4 | D13: 648 | E13: 2592 | F13: 2817.5 | G13: 16.2 | H13: 21.06 | I13: 24.3
A14: B 5 | B14: B | C14: 5 | D14: 673.92 | E14: 2695.68 | F14: 2930.2 | G14: 16.85 | H14: 21.91 | I14: 25.28
A15: B 6 | B15: B | C15: 6 | D15: 700.88 | E15: 2803.52 | F15: 3047.43 | G15: 17.52 | H15: 22.78 | I15: 26.28
... A61: H 10 | B61: H | C61: 10 | D61: 1111.22 | E61: 4444.88 | F61: 4831.58 | G61: 27.78 | H61: 36.11 | I61: 41.67

Sheet Vakantie
A2: 1 | B2: 0 | C2: 16 | D2: < 16 jaar | E2: 22 dagen
A3: 2 | B3: 17 | C3: 18 | D3: 17 en 18 jaar | E3: 23 dagen
A4: 3 | B4: 19 | C4: 39 | D4: 19 t/m 39 jaar | E4: 24 dagen
A5: 4 | B5: 40 | C5: 44 | D5: 40 t/m 44 jaar | E5: 24 dagen
A6: 5 | B6: 45 | C6: 49 | D6: 45 t/m 49 jaar | E6: 25 dagen
A7: 6 | B7: 50 | C7: 54 | D7: 50 t/m 54 jaar | E7: 26 dagen
A8: 7 | B8: 55 | C8: 59 | D8: 55 t/m 59 jaar | E8: 27 dagen
A9: 8 | B9: 60 | C9: 140 | D9: > 60 jaar | E9: 28 dagen
A13: <16 jaar | B13: 28 dagen
A14: 17 en 18 jaar | B14: 26 dagen
A15: 19 t/m 39 jaar | B15: 24 dagen
A16: 40 t/m 44 jaar | B16: 24 dagen
A17: 45 t/m 49 jaar | B17: 25 dagen
A18: 50 t/m 54 jaar | B18: 26 dagen
A19: 55 t/m 59 jaar | B19: 27 dagen
A20: >60 jaar | B20: 28 dagen

Sheet CRM
A1: Accountnaam | B1: Map | C1: Voorletters | D1: Verjardig | E1: BSN Nummer | F1: Postadres | G1: Factuur Plaats | H1: Factuur Postcode | I1: Primaire Telefoon | J1: KvKNummer | K1: IBAN Zakelijk | L1: BTW-ID | M1: Begroeting | N1: Primaire E-Mail | O1: Achternaam
A2: A. Iliev | B2: 1333 | C2: A.N. | D2: 34490 | E2: 694524268 | F2: Springersdiep 21 | G2: s-Gravenhage | H2: 2904ET | I2: +359882707869 | J2: 85495239 | K2: NL | L2: NL004103132B76 | M2: Hr. | N2: aleksandur91@gmail.com | O2: Iliev
A3: A.A. Kazakov | B3: 1074 | C3: A.A. | D3: 28527 | E3: 673253570 | F3: Loosduinseweg 867 | G3: s-Gravenhage | H3: 2571AV | I3: 0685411440 | J3: 82225443 | K3: NL | L3: NL003657916B47 | M3: Hr. | N3: kazakovasen5@gmail.com | O3: Kazakov
A4: A.B. Mitev | B4: 923 | C4: A.B. | D4: 27306 | E4: 454395681 | F4: Dautzenbergstraat 21 | G4: s-Gravenhage | H4: 2523KB | I4: 0684083090 | J4: 76889084 | K4: NL | L4: NL003142606B73 | M4: Hr. | N4: atanas.borisov.mitev@gmail.com | O4: Mitev
A5: A.N.R. Logistics - gemaild - Achterstand BORA | B5: 1583 | C5: V.I. | D5: 32036 | E5: 608580570 | F5: Thijssestraat 215 | G5: s-Gravenhage | H5: 2521ZG | I5: 0624950200 | J5: 92756778 | K5: NL | L5: NL004974407B81 | M5: Hr. | N5: johnnyblaze2fu@gmail.com | O5: Ryazantsev
A6: A.R.S. 89 | B6: 672 | C6: A.R. | D6: 32662 | E6: 395720655 | F6: Jan van der Heijdenstraat 90 | G6: s-Gravenhage | H6: 2522ES | I6: 0638663285 | J6: 73604445 | K6: NL | L6: NL002478396B47 | M6: Hr. | N6: aliosman123987@abv.bg | O6: Shefket
A7: A1 Maatwerk (Tolidar Design VOF) | B7: 698 | C7: A.V. | D7: 29473 | E7: 565284769 | F7: B. Thoenplantsoen 26 | G7: s-Gravenhage | H7: 2552JK | I7: 0612374803 | J7: 73835110 | K7: NL61INGB0006019712 | L7: NL859680484B01 | M7: Hr. | N7: tolidardesign@gmail.com | O7: Volyanyuk
A8: ABZ Bouw | B8: 1680 | C8: Z.D. | D8: 31064 | E8: 398790942 | F8: Van Merlenstraat 58 | G8: s-Gravenhage | H8: 2518TG | I8: 0653958410 | J8: 89949382 | K8: NL | L8: NL004774766B22 | M8: Hr. | N8: zdravkokovachev09@gmail.com | O8: Kovachev
A9: ADI 2018 VOF | B9: 513 | C9: A.S. | D9: 29558 | E9: 545568912 | F9: Jan van der Heydenstraat 4 | G9: s-Gravenhage | H9: 2522EP | I9: 0645025254 | J9: 70947279 | K9: NL | L9: NL858521544B01 | M9: Hr. | N9: anio198@abv.bg | O9: Shopov
A10: AdiMar Bouw | B10: 1541 | C10: A. | D10: 37883 | E10: 664233387 | F10: Obrecht 46 | G10: s-Gravenhage | H10: 2681JM | I10: 0687718709 | J10: 91673569 | K10: NL | L10: NL004907918B89 | M10: Hr. | N10: adrianmarcinczyk5@gmail.com | O10: Marcinczyk
A11: Adix Bouw | B11: 1008 | C11: P.A. | D11: 31271 | E11: 360984940 | F11: Hoefkade 491A | G11: s-Gravenhage | H11: 2525LA | I11: 0684809083 | J11: 78629713 | K11: NL | L11: NL003357920B16 | M11: Hr. | N11: peshoasd85@gmail.com | O11: Mitev
A12: AFM Bouw | B12: 9 | C12: M.Y. | D12: 26169 | E12: 425616083 | F12: Van Diesenstraat 255 | G12: s-Gravenhage | H12: 2521EH | I12: 0620479796 | J12: 56661371 | K12: NL | L12: NL002482305B77 | M12: Hr. | N12: amfbouw1@gmail.com | O12: Filipov
A13: Agora Boekhouding - KOR per 01-04-2023 | B13: 902 | C13: H.A. | D13: 25518 | E13: 255501377 | F13: Burgemeester Elsenlaan 329 | G13: s-Gravenhage | H13: 2282MZ | I13: 0611584401 | J13: 59682132 | K13: NL | L13: NL002447245B76 | M13: Mw. | N13: infoagora69@gmail.com | O13: Tyankova
... A50: Asya Asenova | B50: 1573 | C50: A.H. | D50: 37263 | E50: 691702512 | F50: Beeklaan 215 | G50: s-Gravenhage | H50: 2562AE | I50: +359877177810 | J50: 92556957 | K50: NL | L50: NL004960785B71 | M50: Hr. | N50: asenovaasa566@gmail.com | O50: Asenova
A51: Atka | B51: 1001 | C51: A.A. | D51: 27644 | E51: 660264705 | F51: Paets van Troostwijkstr 53 | G51: s-Gravenhage | H51: 2522DL | I51: 0683871250 | J51: 52955397 | K51: NL | M51: Hr. | N51: atka07@hotmail.com | O51: Sadula
A52: Axentis | B52: 901 | C52: E.J. | D52: 22107 | E52: 126248175 | F52: Steenplaetsstraat 6 | G52: s-Gravenhage | H52: 2288AA | I52: 0707505651 | J52: 55962734 | K52: NL | L52: NL001565172B59 | M52: Hr. | N52: rangelov.e@gmail.com | O52: Rangelov
A53: Ayvaz IJzervlechter | B53: 534 | C53: A.B. | D53: 34268 | E53: 479421663 | F53: Burgersdijkstraat 4 | G53: s-Gravenhage | H53: 2522 WE | I53: 0685350756 | J53: 70060991 | K53: NL | L53: NL002489543B22 | M53: Hr. | N53: nasko_xristev99@icloud.com | O53: Hristev
A54: Azaria | B54: 225 | C54: V.M. | D54: 29109 | E54: 264558704 | F54: Jan Wapstraat 47 | G54: s-Gravenhage | H54: 2523GB | I54: 0628436661 | J54: 56324634 | K54: NL | L54: NL002456577B90 | M54: Mw. | N54: valarina11@hotmail.com | O54: Georgieva
A55: B.A. Nikolov | B55: 1712 | C55: B.A. | D55: 34298 | E55: 346700450 | F55: Hendrik de Keijserstraat 35 | G55: Tilburg | H55: 5041JA | I55: +359885717475 | J55: 97217174 | K55: NL93INGB0114802211 | L55: NL005256357B51 | M55: Hr. | N55: boyanikolov@abv.bg | O55: Nikolov
A56: Babadzhanov SL | B56: 1026 | C56: M.H. | D56: 36389 | E56: 508637922 | F56: Linnaeusstraat 149 | G56: s-Gravenhage | H56: 2522GJ | I56: 0621345253 | J56: 80224636 | K56: NL | L56: NL003409266B10 | M56: Hr. | N56: mehdi.babadjanov@abv.bg | O56: Babadzhanov
A57: Beauty Secret by Tatiana | B57: 1686 | C57: T. | D57: 32332 | E57: 646641402 | F57: Spuiweg 8 | G57: Dordrecht | H57: 3311GV | I57: 0628706549 | J57: 88056333 | K57: NL18INGB0398333882 | L57: NL004531088B51 | M57: Mw. | N57: beautysecretbytatiana@gmail.com | O57: Adamovych
A58: Beko Market | B58: 431 | C58: B.H. | D58: 33525 | E58: 397816194 | F58: Delftselaan 95 | G58: s-Gravenhage | H58: 2512RC | I58: 0611148764 | J58: 69357854 | K58: NL12INGB0007945947 | L58: NL002477801B67 | M58: Hr. | N58: beihan_12@abv.bg | O58: Hyusein
A59: Belkis Schoonmaak - KOR | B59: 37 | C59: Z.G. | D59: 23337 | E59: 548653719 | F59: Maasstraat 131 | G59: s-Gravenhage | H59: 2515 DC | I59: 0644042494 | J59: 57678839 | K59: NL | L59: NL002498851B58 | M59: Mw. | N59: belkisschoonmaak@gmail.com | O59: Filipova
A60: BENEDUKT REPARATIE | B60: 1695 | C60: Y. | D60: 34216 | E60: 384009207 | F60: Ds van den Boschlaan 55 | G60: Rijswijk | H60: 2286PB | I60: 0614229188 | J60: 89972287 | K60: NL | L60: NL004777600B27 | M60: Hr. | N60: benedukt93@gmail.com | O60: Yaroshuk
A61: Beno 80 | B61: 725 | C61: T.B. | D61: 29386 | E61: 264235162 | F61: Lyonnetstraat 49 | G61: s-Gravenhage | H61: 2522NB | I61: 0618345090 | J61: 73948608 | K61: NL | L61: NL002455318B72 | M61: Hr. | N61: vesanke76@gmail.com | O61: Todorov
A62: Betpac | B62: 82 | C62: S.B. | D62: 25796 | E62: 494291849 | F62: Dedemsvaartweg 1138 | G62: s-Gravenhage | H62: 2545BH | I62: 0684077754 | J62: 24468706 | K62: NL | L62: NL002491573B85 | M62: Hr. | N62: shenkoreal@yahoo.com | O62: Shenkov
A63: BG Familia Bakkerij Market | B63: 1671 | C63: G.M. | D63: 34723 | E63: 699541992 | F63: Augustusbloemweg 41 | G63: s-Gravenhage | H63: 1508BB | I63: 0686101008 | J63: 95396977 | K63: NL39INGB0110208196 | L63: NL867114447B01 | M63: Hr. | N63: familiamarket05@gmail.com | O63: Angelov
... A77: Boratech Administraties B.V. | B77: 908 | C77: E.J. | D77: 22107 | E77: 126248175 | F77: Steenplaetsstraat 6 | G77: s-Gravenhage | H77: 2288AA | I77: 0707505651 | J77: 66740975 | K77: NL44INGB0007466288 | L77: NL856680229B01 | M77: Hr. | N77: info@boratech.nl | O77: Rangelov
A78: Boratech Assuranti?n B.V | B78: 1450 | G78: s-Gravenhage | K78: NL
A79: Boratech Assurantiën B.V | B79: 1450 | C79: B.V. | D79: 33132 | E79: 255501237 | F79: Steenplaetsstraat 6 | G79: s-Gravenhage | H79: 2288AA | I79: +31707505651 | J79: 89061136 | K79: NL | L79: NL864866835B01 | M79: Hr. | N79: assurantien@boratech.nl | O79: Fidanchev
A80: Boratech B.V. | B80: 907 | C80: E.J. | D80: 22107 | E80: 126248175 | F80: Steenplaetsstraat 6 | G80: s-Gravenhage | H80: 2288AA | I80: 0707505651 | J80: 66738563 | K80: NL | L80: NL856679343B01 | M80: Hr. | N80: management@boratech.nl | O80: Rangelov
A81: Boratech Personeelsdiensten B.V. | B81: 614 | C81: E.J. | D81: 22107 | E81: 126248175 | F81: Steenplaetsstraat 6 | G81: s-Gravenhage | H81: 2288AA | I81: 0707505651 | J81: 72252324 | K81: NL | L81: NL859047349B01 | M81: Hr. | N81: info@boratechpd.nl | O81: Rangelov
A82: Boratech Trading B.V. | B82: 984 | C82: E.J. | D82: 22107 | E82: 126248175 | F82: Steenplaetsstraat 6 | G82: s-Gravenhage | H82: 2288AA | I82: 0613574628 | J82: 78227690 | K82: NL | L82: NL861310184B01 | M82: Hr. | N82: info@boratechtrading.nl | O82: Rangelov
A83: BoriGol Bouw | B83: 1585 | C83: B.R. | D83: 32881 | E83: 323672231 | F83: Laakkade 189 | G83: s-Gravenhage | H83: 2521XL | I83: 0685774105 | J83: 85935433 | K83: NL | L83: NL004167561B81 | M83: Hr. | N83: rosi_borko@abv.bg | O83: Golemanov
A84: Boris Isolatiebedrijf | B84: 1059 | C84: B.P. | D84: 35848 | E84: 627400838 | F84: Burgemeester Van Haarenlaan 881 | G84: s-Gravenhage | H84: 3119GD | I84: 0657249666 | J84: 81592531 | K84: NL | L84: NL003579946B79 | M84: Hr. | N84: borislavpavlov3232@gmail.com | O84: Pavlov
A85: Borislav Asenov VOF | B85: 1612 | C85: B.M. | D85: 30649 | E85: 510758496 | F85: Hoog Buurlostraat 5 | G85: s-Gravenhage | H85: 2573 HV | I85: 0687797919 | J85: 93778252 | K85: NL | L85: NL866524447B01 | M85: Hr. | N85: mixailovaxristina@gmail.com | O85: Asenov
A86: Borislav Dimov Loonbedrijf | B86: 1090 | C86: B.D. | D86: 35255 | E86: 645456305 | F86: Hulshorststraat 40 | G86: s-Gravenhage | H86: 2573EK | I86: 0684749970 | J86: 97454230 | K86: NL24INGB0113841019 | L86: NL005270940B45 | M86: Hr. | N86: danaildimovv73@gmail.com | O86: Dimov
A87: Borisov Bouw | B87: 1718 | C87: R.I. | D87: 25587 | E87: 525522396 | F87: Drijfriemstraat 27 | G87: s-Gravenhage | H87: 2516XL | I87: 0645923500 | J87: 97909491 | K87: NL | L87: NL005295442B08 | M87: Hr. | N87: rado.borisov@hotmail.com | O87: Borisov
A88: Boro Ijzervlechter | B88: 845 | C88: R.B. | D88: 33522 | E88: 292203305 | F88: Jasmijnstraat 87 | G88: s-Gravenhage | H88: 2563RS | I88: 0685023231 | J88: 75395142 | K88: NL | L88: NL002463419B10 | M88: Hr. | N88: raicho9111@icloud.com | O88: Raykov
A89: Bouwbedrijf Nasko Bogdanov | B89: 773 | C89: N.A. | D89: 28992 | E89: 515860050 | F89: Damasstraat 305 | G89: s-Gravenhage | H89: 2522TS | I89: 0687378815 | J89: 63264161 | K89: NL | L89: NL002494502B11 | M89: Hr. | N89: nde79@abv.bg | O89: Bogdanov
A90: Bovic 2011 | B90: 73 | C90: V.D. | D90: 26018 | E90: 281556763 | F90: Wolweversgaarde 8 | G90: s-Gravenhage | H90: 2542AT | I90: 0620862492 | J90: 64473511 | K90: NL | L90: NL002462438B12 | M90: Hr. | N90: venelinvakov1971@gmail.com | O90: Vakov
... A120: Denis Beheer B.V. | B120: 552 | C120: D.O. | D120: 29191 | E120: 396703744 | F120: Kievit 8 | G120: Barendrecht | H120: 2991ME | I120: 0628813127 | J120: 71249591 | K120: NL02INGB0006220497 | L120: NL858636554B01 | M120: Hr. | N120: algemeen@denis-express.nl | O120: Ibryam
A121: Denis Beheer BV en Denis Express BV Fiscale Eenheid | B121: 552 | C121: D.O. | D121: 29191 | E121: 396703744 | G121: s-Gravenhage | I121: 0628813127 | K121: NL | M121: Hr. | N121: denisbeheerfe@zzp-nl.nl | O121: Ibryam
A122: Denis Express B.V. | B122: 553 | C122: D.O. | D122: 29191 | E122: 396703744 | F122: Gebroken Meeldijk 66 Unit 1.15 | G122: Barendrecht | H122: 2991 VD | I122: 0628813127 | J122: 71254552 | K122: NL | L122: NL858637972B01 | M122: Hr. | N122: Info@denis-express.nl | O122: Ibryam
A123: Denis Kulev 02 | B123: 1303 | C123: D.R. | D123: 37421 | E123: 514911347 | F123: Havendijk 101 | G123: s-Gravenhage | H123: 3114EA | I123: 0628819143 | J123: 85439878 | K123: NL | L123: NL004095429B48 | M123: Hr. | N123: deniskulev26@gmail.com | O123: Kulev
A124: Dennis 90 VOF | B124: 520 | C124: D.M. | D124: 32945 | E124: 486963949 | F124: David Blesstraat 88 | G124: s-Gravenhage | H124: 2526BK | I124: 0638151816 | J124: 70800235 | K124: NL | L124: NL858464834B01 | M124: Hr. | N124: dennis90vof@zzp-nl.nl | O124: Kosov
A125: Dennis_2000 | B125: 1582 | C125: D.Z. | D125: 36747 | E125: 677690083 | F125: Maarsbergenstraat 48 | G125: s-Gravenhage | H125: 2546SR | I125: 0684167398 | J125: 92811868 | K125: NL | L125: NL004977874B15 | M125: Hr. | N125: shterev001@gmail.com | O125: Shterev
A126: Deo Max ZZP | B126: 1654 | C126: M.D. | D126: 31875 | E126: 540159797 | F126: Van Musschenbroekstraat 140 | G126: s-Gravenhage | H126: 2522AV | I126: 0687911768 | J126: 94493685 | K126: NL | L126: NL005089560B52 | M126: Hr. | N126: deqnov.mihail@gmail.com | O126: Deyanov
A127: Depan Consult VOF | B127: 926 | C127: D.G. | D127: 32182 | E127: 567161729 | F127: Lelievaart 66 | G127: s-Gravenhage | H127: 2724SG | I127: 0687826965 | J127: 76986160 | K127: NL | L127: NL860863116B01 | M127: Mw. | N127: jasen1185@gmail.com | O127: Pandova
A128: Dermendzhiev | B128: 1304 | C128: H.A. | D128: 32908 | E128: 571208162 | F128: Werkhovenstraat 3 | G128: s-Gravenhage | H128: 2546VA | I128: 0686322302 | J128: 85734500 | K128: NL | L128: NL004138467B27 | M128: Hr. | N128: hristo0204@gmail.com | O128: Dermendzhiev
A129: Desi Bouw | B129: 455 | C129: T.E. | D129: 26442 | E129: 291068042 | F129: Wolvenrade 29 | G129: s-Gravenhage | H129: 2544VJ | I129: 0682944341 | J129: 67280463 | K129: NL | L129: NL002463275B45 | M129: Hr. | N129: tdelevv@gmail.com | O129: Delev
A130: Desinka 71 | B130: 987 | C130: M.M. | D130: 28057 | E130: 295968527 | F130: Rijkswijkseweg 522 | G130: s-Gravenhage | H130: 2516HT | I130: 0616093154 | J130: 71214852 | K130: NL | L130: NL29596852701 | M130: Hr. | N130: milcho1924@gmail.com | O130: Yordanov
A131: Deston5 | B131: 1236 | C131: А.С. | D131: 28869 | E131: 376512076 | F131: Beijerstraat 142 | G131: s-Gravenhage | H131: 2572BJ | I131: 0639435185 | J131: 67612563 | K131: NL | L131: NL002474861B46 | M131: Hr. | N131: tonimaistor@gmail.com | O131: Maznev
A132: Diana0808 | B132: 1283 | C132: D.S. | D132: 29441 | E132: 642131375 | F132: Nunspeetlaan 383 | G132: s-Gravenhage | H132: 2573GH | I132: 0645639378 | J132: 83908803 | K132: NL | L132: NL003888190B83 | M132: Mw. | N132: dianaatanasova39@gmail.com | O132: Atanasova
A133: DIM | B133: 101 | C133: I.M. | D133: 27836 | E133: 386263565 | F133: Hulshorststraat 6 | G133: s-Gravenhage | H133: 2573EK | I133: 0643820745 | J133: 59797460 | K133: NL | L133: NL002477113B51 | M133: Hr. | N133: daneljan@live.nl | O133: Bakay
... A141: DMK Totaal Afbouw B.V. | B141: 783 | C141: D.M. | D141: 32945 | E141: 486963949 | F141: David Blesstraat 88 | G141: s-Gravenhage | H141: 2526BK | I141: 0638151816 | J141: 74794620 | K141: NL | L141: NL860028902B01 | M141: Hr. | N141: denislavkosov@gmail.com | O141: Kosov
A142: DMK Totaal B.V. | B142: 782 | C142: D.M. | D142: 32945 | E142: 486963949 | F142: David Blesstraat 88 | G142: s-Gravenhage | H142: 2526BK | J142: 74792407 | K142: NL | L142: NL860028185B01 | M142: Hr. | N142: dmktotaal@zzp-nl.nl | O142: Kosov
A143: Donev VOF | B143: 1550 | C143: Y.A. | D143: 32182 | E143: 350715853 | F143: Guido Gezellestraat 7 | G143: s-Gravenhage | H143: 2524CK | I143: 0616030426 | J143: 91483565 | K143: NL | L143: NL865667597B01 | M143: Hr. | N143: qnko_atanasov881988@abv.bg | O143: Donev
A144: Doons Daam | B144: 342 | C144: Y.M. | D144: 28046 | E144: 661849181 | F144: Mijnsherenplein 52B | G144: s-Gravenhage | H144: 3081CT | I144: 0685241538 | J144: 66186846 | K144: NL | L144: NL002512976B03 | M144: Hr. | N144: yuriymanolovdonev@gmail.com | O144: Donev
A145: Dora Onderhoud VOF | B145: 450 | C145: R.M. | D145: 23711 | E145: 350934952 | F145: Goeverneurlaan 571 | G145: s-Gravenhage | H145: 2523CG | I145: 0626590314 | J145: 69735336 | K145: NL46INGB0008019152 | L145: NL857989741B01 | M145: Hr. | N145: marin.marinov5187@gmail.com | O145: Mirchev
A146: Doverie Bouw | B146: 1254 | C146: I.T. | D146: 28748 | E146: 466903728 | F146: Guntersteinweg 383 | G146: s-Gravenhage | H146: 2531KA | I146: 0621371757 | J146: 84568925 | K146: NL16INGB0674729501 | L146: NL003983916B06 | M146: Hr. | N146: vipsitistyle@gmail.com | O146: Todorov
A147: Drago Steigerbouw | B147: 279 | C147: D.D. | D147: 28610 | E147: 264813881 | F147: Jan Wapstraat 90 | G147: s-Gravenhage | H147: 2523GK | I147: 0654113151 | J147: 27318933 | K147: NL | L147: NL002456958B56 | M147: Hr. | N147: ddbonev@abv.bg | O147: Bonev
A148: Dream Future | B148: 1196 | C148: R.I. | D148: 31090 | E148: 580233480 | F148: Garderenstraat 23 | G148: s-Gravenhage | H148: 2573VW | I148: +31687106041 | J148: 82790795 | K148: NL | L148: NL003729174B89 | M148: Mw. | N148: dream2021future@gmail.com | O148: Makedonska
A149: Dream Wild | B149: 1655 | C149: R.G. | D149: 33644 | E149: 457955399 | F149: Melis Stokelaan 195 | G149: s-Gravenhage | H149: 2533CS | I149: 0685261175 | J149: 94583161 | K149: NL | L149: NL005092719B42 | M149: Mw. | N149: dreamwild1992@gmail.com | O149: Genadieva
A150: Dudu VOF | B150: 1400 | C150: Y.A. | D150: 29186 | E150: 267976458 | F150: Velpsestraat 12 | G150: s-Gravenhage | H150: 2573SM | I150: 0681167822 | J150: 87409852 | K150: NL | L150: NL864286454B01 | M150: Hr. | N150: krepost200.om@gmail.com | O150: Mehmed
A151: DVD Trans VOF | B151: 1054 | C151: D.V. | D151: 27972 | E151: 423088713 | F151: Parkdreef 115 | G151: s-Gravenhage | H151: 2724ES | I151: 0614493487 | J151: 92589936 | K151: NL90 INGB 0009 6359 32 | L151: NL866108919B01 | M151: Hr. | N151: dvdtrans19@gmail.com | O151: Vladimirov
A152: Ecomdimi | B152: 1711 | C152: D.T. | D152: 39174 | E152: 661524620 | F152: Minstreelstraat 72 | G152: s-Gravenhage | H152: 2531EE | I152: 0619655222 | J152: 96968966 | K152: NL92INGB0111500737 | L152: NL005241084B59 | M152: Hr. | N152: ecomdimi@gmail.com | O152: Trenov
A153: Edi 2008 VOF | B153: 855 | C153: E.P. | D153: 29040 | E153: 377406491 | F153: Trekweg 197 | G153: Den Haag | H153: 2516SH | I153: 0657401355 | J153: 75936003 | K153: NL82INGB0391293052 | L153: NL860447893B01 | M153: Hr. | N153: edi__2008@hotmail.com | O153: Hadzhiyski
A154: Edi81 VOF | B154: 891 | C154: E.S. | D154: 29914 | E154: 493769407 | F154: Drebbelstraat 304 | G154: s-Gravenhage | H154: 2522DJ | I154: 0610969468 | J154: 76984648 | K154: NL98INGB0007293917 | L154: NL860862781B01 | M154: Hr. | N154: emilhadzhiev81@gmail.com | O154: Hadzhiev
... A165: FA Cleaning Solutions | B165: 841 | C165: F.A. | D165: 28787 | E165: 264187842 | F165: Tamboerijnlaan 179 | G165: Rijswijk | H165: 2287 TG | I165: 0681049378 | J165: 76531775 | K165: NL14INGB0008315772 | L165: NL003091109B80 | M165: Mw. | N165: faa397937@gmail.com | O165: Ahmed
A166: FarmToHome B.V. | B166: 1736 | I166: 0633388115 | J166: 91652081 | K166: NL12INGB0102784205 | L166: NL865725135B01 | N166: maksym@farmtohome.info
A167: Fasma Transport | B167: 710 | C167: I.K. | D167: 29051 | E167: 264280659 | F167: Wolvenrade 21 | G167: s-Gravenhage | H167: 2544VJ | I167: 0616699704 | J167: 27303881 | K167: NL34ABNA0542720477 | L167: NL002455498B04 | M167: Hr. | N167: i.suleymanov@hotmail.com | O167: Syuleymanov
A168: FEA Loonbedrijf | B168: 1442 | C168: A.A. | D168: 30114 | E168: 675952967 | F168: Linnaeusstraat 149 | G168: s-Gravenhage | H168: 2522GJ | I168: 0618389007 | J168: 78496330 | K168: NL30INGB0006532818 | L168: NL003337539B18 | M168: Mw. | N168: feqmollova82@gmail.com | O168: Molla
A169: Feimov (Castle Trans) | B169: 1326 | C169: A.F. | D169: 27791 | E169: 264138764 | F169: Convivastraat 21 | G169: s-Gravenhage | H169: 2522XD | I169: 0617104403 | J169: 27344296 | K169: NL03INGB0005065597 | L169: NL002455930B93 | M169: Hr. | N169: feimov.zzp@gmail.com | O169: Ahmedov
A170: FF Solar (Bulgarian Ticket Center) | B170: 34 | C170: F.F. | D170: 23787 | E170: 250920724 | F170: Jan Vosstraat 78 | G170: s-Gravenhage | H170: 2533TZ | I170: 0682500708 | J170: 57607060 | K170: NL | L170: NL002440760B47 | M170: Hr. | N170: f.kehayov@hotmail.com | O170: Kehayov
A171: Fifty Seas B.V. | B171: 1742 | F171: Hullenbergweg 278 | G171: Amsterdam | H171: 1101BV | J171: 92252990 | K171: NL | L171: NL865957502B01
A172: Filip V.O.F. | B172: 866 | C172: F.A. | D172: 29942 | E172: 363298289 | F172: Miamihof 36 | G172: s-Gravenhage | H172: 2548JB | I172: 0641098978 | J172: 76117863 | K172: NL90INGB0006817597 | L172: NL860513609B01 | M172: Hr. | N172: filip.shetev@gmail.com | O172: Shetev
A173: FISCALE EENHEID Sol Works en Solaris Montage | B173: 378 | C173: V.P. | D173: 29208 | E173: 264594356 | F173: Stephensonstraat 123 | G173: Hoogeveen | H173: 7903AS | K173: NL | L173: NL826184352B01 | M173: Hr. | O173: Peev
A174: Flyover Solutions | B174: 1188 | C174: T.V. | D174: 32971 | E174: 692309317 | F174: Damasstraat 172 | G174: s-Gravenhage | H174: 2522TZ | I174: 0633257510 | J174: 82727686 | K174: NL56INGB0109267281 | L174: NL003718326B42 | M174: Hr. | N174: info@flyoversolutions.nl | O174: Velev
A175: FOT Bouw | B175: 1034 | C175: V.S. | D175: 34494 | E175: 604551976 | F175: Linnaeusstraat 96 | G175: s-Gravenhage | H175: 2522GV | I175: 0657836755 | J175: 80729339 | K175: NL07INGB0009606192 | L175: NL003477665B78 | M175: Hr. | N175: vasilfotev7@gmail.com | O175: Fotev
A176: Galenda | B176: 566 | C176: M.A. | D176: 36165 | E176: 623918250 | F176: Werkzijde 27 | G176: s-Gravenhage | H176: 2543CA | I176: +31633357772 | J176: 71439684 | K176: NL | L176: NL623918250B01 | M176: Hr. | N176: misha.galenda@gmail.com | O176: Galenda
A177: GALIN | B177: 1258 | C177: G.S. | D177: 30674 | E177: 336918069 | F177: Alberdingk Thijmstraat 180 | G177: s-Gravenhage | H177: 2524HR | I177: 0684801782 | J177: 69487677 | K177: NL66INGB0008010353 | L177: NL002470593B46 | M177: Hr. | N177: galin.12@hotmail.com | O177: Georgiev
A178: GAV Diensten | B178: 1567 | C178: G.A. | D178: 33766 | E178: 295409940 | F178: Cilliersstraat 11 | G178: s-Gravenhage | H178: 2572 AS | I178: 0613878420 | J178: 92475663 | K178: NL22 INGB 0104 7511 85 | L178: NL004959404B84 | M178: Hr. | N178: velkovgosho914@gmail.com | O178: Velkov
A179: GDP Bouw | B179: 416 | C179: G.D. | D179: 28424 | E179: 368962258 | F179: Van Anrooijstraat 10 | G179: Oss | H179: 5343BC | I179: 0685070458 | J179: 68955189 | K179: NL14INGB0007712335 | L179: NL002474214B49 | M179: Hr. | N179: gpanayotov77@gmail.com | O179: Panayotov
A180: Georgi 0609 | B180: 1455 | C180: A.G. | D180: 35621 | E180: 388340022 | F180: Bouwlustlaan 34 | G180: s-Gravenhage | H180: 2544JT | I180: 0685482485 | J180: 89016262 | K180: NL17INGB0101658915 | L180: NL004681218B91 | M180: Hr. | N180: asen.velev9710@gmail.com | O180: Velev
A181: Georgi Bouwservice | B181: 911 | C181: G.D. | D181: 27264 | E181: 522111026 | F181: Oostvaardersdijk 26 | G181: Lelystad | H181: 8243PA | I181: 0687889604 | J181: 77121104 | K181: NL23INGB0006263187 | L181: NL003151016B43 | M181: Hr. | N181: georgi-ristana@hotmail.com | O181: Tsvetanov
A182: Germaneca | B182: 1483 | C182: N.S. | D182: 30414 | E182: 577739700 | F182: Naarderstraat 149 | G182: s-Gravenhage | H182: 2574PE | I182: 0633157131 | J182: 73668672 | K182: NL52INGB0008874584 | L182: NL002502702B28 | M182: Hr. | N182: geroashikov@gmail.com | O182: Ashikov
A183: GGG Bouw | B183: 638 | C183: G.I. | D183: 31166 | E183: 509444374 | F183: 1e van Leyden Gaelstraat 394 | G183: Vlaardingen | H183: 3134 LE | I183: 0628860469 | J183: 72717890 | K183: NL28INGB0008626890 | L183: NL002493680B37 | M183: Hr. | N183: jorogipsa@yahoo.com | O183: Atanasov
A184: Ginev Services | B184: 1274 | C184: H.K. | D184: 33037 | E184: 686287319 | F184: Hongarenburg 557 | G184: s-Gravenhage | H184: 2591VV | I184: 0645354013 | J184: 96925264 | K184: NL41INGB0675089018 | L184: NL005250013B14 | M184: Hr. | N184: icooo_icooo@abv.bg | O184: Ginev
A185: Gocha Bouw | B185: 761 | C185: G. | D185: 30647 | E185: 259988595 | F185: Floris Burgwal 173 | G185: Capelle aan den IJssel | H185: 2907PE | I185: 0614536262 | J185: 74579541 | K185: NL15INGB0009222219 | L185: NL002451035B13 | M185: Hr. | N185: cavejskigoran@gmail.com | O185: Cavejski
... A257: Kremaborko | B257: 1478 | C257: P.G. | D257: 34134 | E257: 672970594 | F257: Oudemansstraat 179 | G257: s-Gravenhage | H257: 2522SH | I257: 0687649327 | J257: 89160347 | K257: NL05INGB0101289367 | L257: NL004699465B89 | M257: Hr. | N257: pavlinzlatanov3@gmail.com | O257: Zlatanov
A258: Kriandr Services VOF | B258: 380 | C258: A.M. | D258: 25550 | E258: NL866847947B01 | F258: Werkzijde 27 | G258: s-Gravenhage | H258: 2543CA | I258: +31611583335 | J258: 94649553 | K258: NL85INGB0004259409 | L258: NL866847947B01 | M258: Hr. | N258: kriandr88@gmail.com | O258: Galenda
A259: Krushkov98 | B259: 1713 | C259: V.V. | D259: 35934 | E259: 543314868 | F259: Van Zeggelenlaan 346 | G259: s-Gravenhage | H259: 2524BB | I259: 0682795406 | J259: 97360163 | K259: NL | L259: NL005266012B68 | M259: Hr. | N259: velizarkrushkov@gmail.com | O259: Krushkov
A260: KTM Bouw | B260: 684 | C260: T. | D260: 30203 | E260: 483624639 | F260: Houtrustweg 396 | G260: s-Gravenhage | H260: 2583EX | I260: 0684389962 | J260: 73887390 | K260: NL17INGB0008977064 | L260: NL002490129B83 | M260: Hr. | N260: tkalyatyak@gmail.com | O260: Kalytiak
A261: Kumanov ZZP | B261: 876 | C261: I.V. | D261: 29242 | E261: 589515937 | F261: Vreeswijkstraat 441 | G261: s-Gravenhage | H261: 2546AM | I261: 0685476167 | J261: 93862326 | K261: NL83INGB0007564817 | L261: NL005048673B17 | M261: Hr. | N261: anitosheva86@gmail.com | O261: Kumanov
A262: Kuzmanov Bouw | B262: 1710 | C262: K.B. | D262: 27376 | E262: NL316129604B01 | F262: Oudemansstraat 382 | G262: s-Gravenhage | H262: 2522TG | I262: 0616398813 | J262: 97218359 | K262: NL65INGB0114437122 | L262: NL005256514B93 | M262: Hr. | N262: kaloyan.borisov74@gmail.com | O262: Kuzmanov
A263: KVL Bouw B.V. | B263: 1741 | C263: M.V. | D263: 28790 | E263: 398636928 | F263: Janssoniusstraat 11 | G263: s-Gravenhage | H263: 2523HA | I263: +31617168484 | J263: 98527509 | K263: NL | L263: NL868533543B01 | M263: Hr. | N263: 2kolia21101978@gmail.com | O263: Lanko
A264: Lavendel Schoonmaakbedrijf | B264: 988 | C264: S.M. | D264: 31075 | E264: 680253646 | F264: Oranjelaan 12 | G264: t Veld | H264: 1735 HR | I264: 0638926821 | J264: 78287391 | K264: NL10INGB0009573837 | L264: NL003312995B45 | M264: Mw. | N264: seydehyuseinova@yahoo.co.uk | O264: Hyuseinova
A265: LBSH Service | B265: 525 | C265: L.B. | D265: 30832 | E265: 438696803 | F265: Springersdiep 21 | G265: Capelle aan den IJssel | H265: 2904ET | I265: +359878548781 | J265: 69851247 | K265: NL | L265: NL002484003B24 | M265: Hr. | N265: kanji_1@abv.bg | O265: Shiboykov
A266: LHV Bouw | B266: 320 | C266: L.H. | D266: 27214 | E266: 478470344 | F266: Alpherwetering 20 | G266: Waddinxveen | H266: 2741 MN | I266: 0643743812 | J266: 66279585 | K266: NL56INGB0007385562 | L266: NL002489378B52 | M266: Hr. | N266: lhv.bouw@gmail.com | O266: Varaykov
...
